generator.v
module probador(clk,rst,acknowledge,validdata);
output clk,rst,acknowledge,validdata;

reloj r1(clk);
reset rs(rst);
ack a1(acknowledge);
valid d1(validdata);
endmodule
//generacion del reloj
module reloj(clk);
output clk;
reg clk;  
initial
  begin 
 
  clk =0;
  end
  always
	begin
   #250 clk =1;
   #250 clk =0;
   
	end
endmodule
//generacion del reset
module reset (rst);
output rst;
reg rst;
initial
	begin
	 rst=0;
	#2 rst=~rst;
	#600 rst=~rst;
	end
endmodule

module ack (acknowledge);
output acknowledge;
reg acknowledge;
initial
	begin
	
	 acknowledge=0;
	#20000 acknowledge=~acknowledge;
	#400 acknowledge=~acknowledge;
	end
endmodule

module valid (validdata);
output validdata;
reg validdata;
initial
	begin
	
	validdata=0;
	#1000 validdata=~validdata;
	#500 validdata=~validdata;
	end
endmodule

controlMachine.v

`define STATE_IDLE 0
`define STATE_CALC 1
`define STATE_DONE 2





//------------------------------------------------



module control_Machine
  (
    input wire Clock,
    input wire Reset,
    input wire iLSB,   
    input wire iValid_Data,
    input wire iAck,
    output reg oShift,
    output reg  oA_Sel,
    output reg oB_Sel,
    output reg oProduct_Sel,
    output reg oAdd_Sel
  );
  //Registros  internos del controlador
  
  reg [5:0] rCounter;
  reg [7:0]rCurrentState;
  reg  [7:0]rNextState;
  reg rCountReset;

  //Next State and delay logic
  always @ ( posedge Clock )
    if (Reset)
      begin
        rCurrentState = `STATE_IDLE;
        rCountReset <=1'b1;
       
      end
  else
		begin
      rCurrentState <= rNextState;
      if(rCountReset)
      begin
      rCounter<= 6'd0;
      end
      
      else
      
     begin
     rCounter<=  rCounter + 6'd1;
     end
		end
    

  //----------------------------------------------
  //Current state and output logic
  always @ ( * )
    begin
      case (rCurrentState)
        //------------------------------------------
        `STATE_IDLE:
          begin
          rCountReset=1'b1;
          oShift=1'b0;
         oA_Sel=1'b0;
         oB_Sel=1'b0;
         oProduct_Sel=1'b0;
         oAdd_Sel=1'b0;
         if(iValid_Data)
			begin
            rNextState = `STATE_CALC;
            rCountReset=1'b0;
            end
          else
			begin
			rNextState= `STATE_IDLE;
			end
          end
//------------------------------------------
/*

*/
      `STATE_CALC:
        begin
         oA_Sel=1;
         oB_Sel=1;
            oProduct_Sel=1;
         if(iLSB)
         begin
           oShift=1;
           end
           else
           begin
           oShift=1;
           oAdd_Sel=1;
           end
       if(rCounter<6'd32)
       begin
       rNextState=`STATE_CALC;
       end    
       else
       begin 
        rNextState=`STATE_DONE;
         rCountReset=1'b1;
       end
          
          
          
          
        end
//------------------------------------------
/*

  */
      `STATE_DONE:
        begin
          rCounter= 6'd0;
          oShift=1'b0;
         oAdd_Sel=1'b0;
          if ( iAck)
            rNextState = `STATE_IDLE;
          else
            rNextState = `STATE_DONE;
        end

//------------------------------------------
        
 
        default:
          begin
            rNextState = `STATE_IDLE;
          end
        //------------------------------------------
      endcase
    end
endmodule

testbench.v
`timescale 1ns/1ps
`include "controlMachine.v"
`include "generator.v"
module BancoPruebas;
wire Clock,Reset,wAck,wValidData;
wire oShift,oA_Sel,oB_Sel, oProduct_Sel,oAdd_Sel;
control_Machine control1(.Clock(Clock),.Reset(Reset),.iLSB(1'b1),.iValid_Data(wValidData),.iAck(wAck),.oShift(oShift),.oA_Sel(oA_Sel),.oB_Sel(oB_Sel),.oProduct_Sel(oProduct_Sel),.oAdd_Sel(oAdd_Sel));
probador p1(.clk(Clock),.rst(Reset),.acknowledge(wAck),.validdata(wValidData));
 initial 
  begin
    $dumpfile("signals.vcd");
    $dumpvars;
    #67000 ;
    $display ("Test finished");
    $finish;
   
  end
endmodule

signals.vcd
$date
	Wed May  6 19:52:24 2015
$end
$version
	Icarus Verilog
$end
$timescale
	1ps
$end
$scope module BancoPruebas $end
$var wire 1 ! Clock $end
$var wire 1 " Reset $end
$var wire 1 # oA_Sel $end
$var wire 1 $ oAdd_Sel $end
$var wire 1 % oB_Sel $end
$var wire 1 & oProduct_Sel $end
$var wire 1 ' oShift $end
$var wire 1 ( wAck $end
$var wire 1 ) wValidData $end
$scope module control1 $end
$var wire 1 ! Clock $end
$var wire 1 " Reset $end
$var wire 1 ( iAck $end
$var wire 1 * iLSB $end
$var wire 1 ) iValid_Data $end
$var reg 1 + oA_Sel $end
$var reg 1 , oAdd_Sel $end
$var reg 1 - oB_Sel $end
$var reg 1 . oProduct_Sel $end
$var reg 1 / oShift $end
$var reg 1 0 rCountReset $end
$var reg 6 1 rCounter [5:0] $end
$var reg 8 2 rCurrentState [7:0] $end
$var reg 8 3 rNextState [7:0] $end
$upscope $end
$scope module p1 $end
$var wire 1 ( acknowledge $end
$var wire 1 ! clk $end
$var wire 1 " rst $end
$var wire 1 ) validdata $end
$scope module r1 $end
$var reg 1 4 clk $end
$upscope $end
$scope module rs $end
$var reg 1 5 rst $end
$upscope $end
$scope module a1 $end
$var reg 1 6 acknowledge $end
$upscope $end
$scope module d1 $end
$var reg 1 7 validdata $end
$upscope $end
$upscope $end
$upscope $end
$enddefinitions $end
#0
$dumpvars
07
06
05
04
b0 3
bx 2
bx 1
x0
x/
x.
x-
x,
x+
1*
0)
0(
x'
x&
x%
x$
x#
0"
0!
$end
#2000
15
1"
#250000
0,
0$
0.
0&
0-
0%
0+
0#
0/
0'
10
b0 2
14
1!
#500000
04
0!
#602000
05
0"
#750000
b0 1
14
1!
#1000000
00
b1 3
04
0!
17
1)
#1250000
1/
1'
1.
1&
1-
1%
1+
1#
b1 1
b1 2
14
1!
#1500000
04
0!
07
0)
#1750000
b10 1
14
1!
#2000000
04
0!
#2250000
b11 1
14
1!
#2500000
04
0!
#2750000
b100 1
14
1!
#3000000
04
0!
#3250000
b101 1
14
1!
#3500000
04
0!
#3750000
b110 1
14
1!
#4000000
04
0!
#4250000
b111 1
14
1!
#4500000
04
0!
#4750000
b1000 1
14
1!
#5000000
04
0!
#5250000
b1001 1
14
1!
#5500000
04
0!
#5750000
b1010 1
14
1!
#6000000
04
0!
#6250000
b1011 1
14
1!
#6500000
04
0!
#6750000
b1100 1
14
1!
#7000000
04
0!
#7250000
b1101 1
14
1!
#7500000
04
0!
#7750000
b1110 1
14
1!
#8000000
04
0!
#8250000
b1111 1
14
1!
#8500000
04
0!
#8750000
b10000 1
14
1!
#9000000
04
0!
#9250000
b10001 1
14
1!
#9500000
04
0!
#9750000
b10010 1
14
1!
#10000000
04
0!
#10250000
b10011 1
14
1!
#10500000
04
0!
#10750000
b10100 1
14
1!
#11000000
04
0!
#11250000
b10101 1
14
1!
#11500000
04
0!
#11750000
b10110 1
14
1!
#12000000
04
0!
#12250000
b10111 1
14
1!
#12500000
04
0!
#12750000
b11000 1
14
1!
#13000000
04
0!
#13250000
b11001 1
14
1!
#13500000
04
0!
#13750000
b11010 1
14
1!
#14000000
04
0!
#14250000
b11011 1
14
1!
#14500000
04
0!
#14750000
b11100 1
14
1!
#15000000
04
0!
#15250000
b11101 1
14
1!
#15500000
04
0!
#15750000
b11110 1
14
1!
#16000000
04
0!
#16250000
b11111 1
14
1!
#16500000
04
0!
#16750000
10
b10 3
b100000 1
14
1!
#17000000
04
0!
#17250000
0/
0'
b0 1
b10 2
14
1!
#17500000
04
0!
#17750000
14
1!
#18000000
04
0!
#18250000
14
1!
#18500000
04
0!
#18750000
14
1!
#19000000
04
0!
#19250000
14
1!
#19500000
04
0!
#19750000
14
1!
#20000000
b0 3
04
0!
16
1(
#20250000
0.
0&
0-
0%
0+
0#
b0 2
14
1!
#20400000
06
0(
