DataPath.v
module DataPath
(
	input wire b_sel,
	input wire a_sel,
	input wire add_sel,
	input wire prod_sel,
	input wire [31:0]iData_A,
	input wire [31:0]iData_B,
	input wire Shift_Enable,
	input wire Clock,
	input wire Reset,
	output reg [63:0]Prod,
	output reg oB_LSB

);

//-------------PARA B-----------------//
wire [31:0]Mux_B_Out;
wire [31:0]Reg_B_Out;
wire [31:0]Shifted_B;

always @(Reg_B_Out[0])
	oB_LSB= Reg_B_Out[0];

MUX #(32) Mux_B
(
	.Select(b_sel),
	.Data_A(Shifted_B),
	.Data_B(iData_B),
	.Out(Mux_B_Out)
);

FFD #(32) Reg_B
(
	.Clock(Clock),
	.Reset(Reset),
	.Enable(1),
	.D(Mux_B_Out),
	.Q(Reg_B_Out)
	
);

Shift_Register_Right Shift_B
(	
	.Data(Reg_B_Out),
	.Enable(Shift_Enable),
	.Shifted_Data(Shifted_B)
);

//--------PARA A----------//
wire [31:0]Mux_A_Out;
wire [31:0]Reg_A_Out;
wire [31:0]Shifted_A;

MUX #(32) Mux_A
(
	.Select(a_sel),
	.Data_A(Shifted_A),
	.Data_B(iData_A),
	.Out(Mux_A_Out)
);

FFD #(32) Reg_A
(
	.Clock(Clock),
	.Reset(Reset),
	.Enable(1),
	.D(Mux_A_Out),
	.Q(Reg_A_Out)
	
);

Shift_Register_Left Shift_A
(	
	.Data(Reg_A_Out),
	.Enable(Shift_Enable),
	.Shifted_Data(Shifted_A)
);

//--------PARA EL PRODUCTO------------//
wire [63:0]Mux_Prod_Out;
wire [63:0]Add_Out;
wire [63:0]Sum_Prod;

MUX #(64) Mux_Prod1
(
	.Select(prod_sel),
	.Data_A(Sum_Prod),
	.Data_B(64'b0),
	.Out(Mux_Prod_Out)
);

wire [63:0]Product;
always @ (Product)
	Prod=Product;
	
FFD #(64) Reg_Prod
(
	.Clock(Clock),
	.Reset(Reset),
	.Enable(1),
	.D(Mux_Prod_Out),
	.Q(Product)
);

ADDER Adder_Prod
(

	.Data_A(Reg_A_Out),
	.Data_B(Prod),
	.Result(Add_Out)
);

MUX #(64) Mux_Prod0
(
	.Select(add_sel),
	.Data_A(Product),//Add_Out
	.Data_B(Add_Out),//Product
	.Out(Sum_Prod)
);
endmodule


///////////////////MUX//////////////////
module MUX #(parameter SIZE=32)
(
	input wire Select,
	input wire [SIZE-1:0]Data_B,
	input wire [SIZE-1:0]Data_A,
	output reg [SIZE-1:0] Out
);


always @(*)
	begin
		if(Select==0)
			Out=Data_A;
		else if (Select==1)
			Out=Data_B;
	end

endmodule

///////////////REGISTER///////////////
module FFD # ( parameter SIZE=32 )
(
	input wire				Clock,
	input wire				Reset,
	input wire				Enable,
	input wire [SIZE-1:0]	D,
	output reg [SIZE-1:0]	Q
);


always @ (posedge Clock) 
begin
	if ( Reset )
		Q <= 0;
	else
	begin	
		if (Enable) 
			Q <= D; 
	end	
 
end

endmodule

////////////////SHIFT REGISTER RIGHT//////////
module Shift_Register_Right
(
	input wire [31:0]Data,
	input wire Enable,
	output reg [31:0]Shifted_Data
);
	
	always @ (Data)
		begin
			Shifted_Data = Data>>1;
		end

endmodule

////////////SHIFT REGISTER LEFT//////////////
module Shift_Register_Left
(
	input wire [31:0]Data,
	input wire Enable,
	output reg [31:0]Shifted_Data
);
	
	always @ (Enable )
		begin
			Shifted_Data = Data<<1;
		end

endmodule

////////////ADDER///////////////////////////
module ADDER
(
	input wire [31:0]Data_A,
	input wire [63:0]Data_B,
	output reg [63:0]Result
);

	always @(*)
		begin
			Result = Data_B + Data_A;
		end
endmodule

generator.v
module probador(clk,rst,acknowledge,validdata);
output clk,rst,acknowledge,validdata;

reloj r1(clk);
reset rs(rst);
ack a1(acknowledge);
valid d1(validdata);
endmodule
//generacion del reloj
module reloj(clk);
output clk;
reg clk;  
initial
  begin 
 
  clk =0;
  end
  always
	begin
   #250 clk =1;
   #250 clk =0;
   
	end
endmodule
//generacion del reset
module reset (rst);
output rst;
reg rst;
initial
	begin
	 rst=0;
	#2 rst=~rst;
	#600 rst=~rst;
	end
endmodule

module ack (acknowledge);
output acknowledge;
reg acknowledge;
initial
	begin
	
	 acknowledge=0;
	#20000 acknowledge=~acknowledge;
	#400 acknowledge=~acknowledge;
	end
endmodule

module valid (validdata);
output validdata;
reg validdata;
initial
	begin
	
	validdata=0;
	#1000 validdata=~validdata;
	#500 validdata=~validdata;
	end
endmodule

controlMachine.v

`define STATE_IDLE 0
`define STATE_CALC 1
`define STATE_DONE 2





//------------------------------------------------



module control_Machine
  (
    input wire Clock,
    input wire Reset,
    input wire iLSB,   
    input wire iValid_Data,
    input wire iAck,
    output reg oShift,
    output reg  oA_Sel,
    output reg oB_Sel,
    output reg oProduct_Sel,
    output reg oAdd_Sel
  );
  //Registros  internos del controlador
  
  reg [5:0] rCounter;
  reg [1:0]rCurrentState;
  reg  [1:0]rNextState;
  reg rCountReset;

  //Next State and delay logic
  always @ ( posedge Clock )
    if (Reset)
      begin
        rCurrentState = `STATE_IDLE;
        rCountReset <=1'b1;
       
      end
  else
		begin
      rCurrentState <= rNextState;
      if(rCountReset)
      begin
      rCounter<= 6'd0;
      end
      
      else
      
     begin
     rCounter<=  rCounter + 6'd1;
     end
		end
    

  //----------------------------------------------
  //Current state and output logic
  always @ ( * )
    begin
      case (rCurrentState)
        //------------------------------------------
        `STATE_IDLE:
          begin
          rCountReset=1'b1;
          oShift=1'b0;
         oA_Sel=1'b0;
         oB_Sel=1'b0;
         oProduct_Sel=1'b0;
         oAdd_Sel=1'b0;
         if(iValid_Data)
			begin
            rNextState = `STATE_CALC;
            rCountReset=1'b0;
            end
          else
			begin
			rNextState= `STATE_IDLE;
			end
          end
//------------------------------------------
/*

*/
      `STATE_CALC:
        begin
         oA_Sel=1;
         oB_Sel=1;
            oProduct_Sel=1;
         if(iLSB)
         begin
           oShift=1;
           end
           else
           begin
           oShift=1;
           oAdd_Sel=1;
           end
       if(rCounter<6'd32)
       begin
       rNextState=`STATE_CALC;
       end    
       else
       begin 
        rNextState=`STATE_DONE;
         rCountReset=1'b1;
       end
          
          
          
          
        end
//------------------------------------------
/*

  */
      `STATE_DONE:
        begin
          rCounter= 6'd0;
          oShift=1'b0;
         oAdd_Sel=1'b0;
          if ( iAck)
            rNextState = `STATE_IDLE;
          else
            rNextState = `STATE_DONE;
        end

//------------------------------------------
        
 
        default:
          begin
            rNextState = `STATE_IDLE;
          end
        //------------------------------------------
      endcase
    end
endmodule

testbench.v
`timescale 1ns/1ps
`include "controlMachine.v"
`include "generator.v"
`include "DataPath.v"
module BancoPruebas;
wire Clock,Reset,wAck,wValidData;
wire oShift,oA_Sel,oB_Sel, oProduct_Sel,oAdd_Sel, wiLSB;
reg [31:0] dataA=32'd10;
reg [31:0] dataB=32'd349525;
wire [63:0] product;

control_Machine control1(.Clock(Clock),.Reset(Reset),.iLSB(wiLSB),.iValid_Data(wValidData),.iAck(wAck),.oShift(oShift),.oA_Sel(oA_Sel),.oB_Sel(oB_Sel),.oProduct_Sel(oProduct_Sel),.oAdd_Sel(oAdd_Sel));
probador p1(.clk(Clock),.rst(Reset),.acknowledge(wAck),.validdata(wValidData));

DataPath data1(
	.b_sel(oB_Sel), .a_sel(oA_Sel), .add_sel(oAdd_Sel),.prod_sel(oProduct_Sel), .iData_A(dataA), .iData_B(dataB), .Shift_Enable(oShift), .Clock(Clock), .Reset(Reset), .Prod(product), .oB_LSB(wiLSB));



 initial 
  begin
    $dumpfile("signals.vcd");
    $dumpvars;
    #35000 ;
    $display ("Test finished");
    $finish;
   
  end
endmodule

signals.vcd
$date
	Sun May 10 16:21:37 2015
$end
$version
	Icarus Verilog
$end
$timescale
	1ps
$end
$scope module BancoPruebas $end
$var wire 1 ! Clock $end
$var wire 1 " Reset $end
$var wire 1 # oA_Sel $end
$var wire 1 $ oAdd_Sel $end
$var wire 1 % oB_Sel $end
$var wire 1 & oProduct_Sel $end
$var wire 1 ' oShift $end
$var wire 64 ( product [63:0] $end
$var wire 1 ) wAck $end
$var wire 1 * wValidData $end
$var wire 1 + wiLSB $end
$var reg 32 , dataA [31:0] $end
$var reg 32 - dataB [31:0] $end
$scope module control1 $end
$var wire 1 ! Clock $end
$var wire 1 " Reset $end
$var wire 1 ) iAck $end
$var wire 1 + iLSB $end
$var wire 1 * iValid_Data $end
$var reg 1 . oA_Sel $end
$var reg 1 / oAdd_Sel $end
$var reg 1 0 oB_Sel $end
$var reg 1 1 oProduct_Sel $end
$var reg 1 2 oShift $end
$var reg 1 3 rCountReset $end
$var reg 6 4 rCounter [5:0] $end
$var reg 2 5 rCurrentState [1:0] $end
$var reg 2 6 rNextState [1:0] $end
$upscope $end
$scope module p1 $end
$var wire 1 ) acknowledge $end
$var wire 1 ! clk $end
$var wire 1 " rst $end
$var wire 1 * validdata $end
$scope module r1 $end
$var reg 1 7 clk $end
$upscope $end
$scope module rs $end
$var reg 1 8 rst $end
$upscope $end
$scope module a1 $end
$var reg 1 9 acknowledge $end
$upscope $end
$scope module d1 $end
$var reg 1 : validdata $end
$upscope $end
$upscope $end
$scope module data1 $end
$var wire 64 ; Add_Out [63:0] $end
$var wire 1 ! Clock $end
$var wire 32 < Mux_A_Out [31:0] $end
$var wire 32 = Mux_B_Out [31:0] $end
$var wire 64 > Mux_Prod_Out [63:0] $end
$var wire 64 ? Product [63:0] $end
$var wire 32 @ Reg_A_Out [31:0] $end
$var wire 32 A Reg_B_Out [31:0] $end
$var wire 1 " Reset $end
$var wire 1 ' Shift_Enable $end
$var wire 32 B Shifted_A [31:0] $end
$var wire 32 C Shifted_B [31:0] $end
$var wire 64 D Sum_Prod [63:0] $end
$var wire 1 # a_sel $end
$var wire 1 $ add_sel $end
$var wire 1 % b_sel $end
$var wire 32 E iData_A [31:0] $end
$var wire 32 F iData_B [31:0] $end
$var wire 1 & prod_sel $end
$var reg 64 G Prod [63:0] $end
$var reg 1 H oB_LSB $end
$scope module Mux_B $end
$var wire 32 I Data_A [31:0] $end
$var wire 32 J Data_B [31:0] $end
$var wire 1 % Select $end
$var reg 32 K Out [31:0] $end
$upscope $end
$scope module Reg_B $end
$var wire 1 ! Clock $end
$var wire 32 L D [31:0] $end
$var wire 1 M Enable $end
$var wire 1 " Reset $end
$var reg 32 N Q [31:0] $end
$upscope $end
$scope module Shift_B $end
$var wire 32 O Data [31:0] $end
$var wire 1 ' Enable $end
$var reg 32 P Shifted_Data [31:0] $end
$upscope $end
$scope module Mux_A $end
$var wire 32 Q Data_A [31:0] $end
$var wire 32 R Data_B [31:0] $end
$var wire 1 # Select $end
$var reg 32 S Out [31:0] $end
$upscope $end
$scope module Reg_A $end
$var wire 1 ! Clock $end
$var wire 32 T D [31:0] $end
$var wire 1 U Enable $end
$var wire 1 " Reset $end
$var reg 32 V Q [31:0] $end
$upscope $end
$scope module Shift_A $end
$var wire 32 W Data [31:0] $end
$var wire 1 ' Enable $end
$var reg 32 X Shifted_Data [31:0] $end
$upscope $end
$scope module Mux_Prod1 $end
$var wire 64 Y Data_A [63:0] $end
$var wire 64 Z Data_B [63:0] $end
$var wire 1 & Select $end
$var reg 64 [ Out [63:0] $end
$upscope $end
$scope module Reg_Prod $end
$var wire 1 ! Clock $end
$var wire 64 \ D [63:0] $end
$var wire 1 ] Enable $end
$var wire 1 " Reset $end
$var reg 64 ^ Q [63:0] $end
$upscope $end
$scope module Adder_Prod $end
$var wire 32 _ Data_A [31:0] $end
$var wire 64 ` Data_B [63:0] $end
$var reg 64 a Result [63:0] $end
$upscope $end
$scope module Mux_Prod0 $end
$var wire 64 b Data_A [63:0] $end
$var wire 64 c Data_B [63:0] $end
$var wire 1 $ Select $end
$var reg 64 d Out [63:0] $end
$upscope $end
$upscope $end
$upscope $end
$enddefinitions $end
#0
$dumpvars
bx d
bx c
bx b
bx a
bx `
bx _
bx ^
1]
bx \
bx [
b0 Z
bx Y
bx X
bx W
bx V
1U
bx T
bx S
b1010 R
bx Q
bx P
bx O
bx N
1M
bx L
bx K
b1010101010101010101 J
bx I
xH
bx G
b1010101010101010101 F
b1010 E
bx D
bx C
bx B
bx A
bx @
bx ?
bx >
bx =
bx <
bx ;
0:
09
08
07
b0 6
bx 5
bx 4
x3
x2
x1
x0
x/
x.
b1010101010101010101 -
b1010 ,
x+
0*
0)
bx (
x'
x&
x%
x$
x#
0"
0!
$end
#2000
18
1"
#250000
0H
0+
b0 K
b0 =
b0 L
b0 [
b0 >
b0 \
b0 P
b0 C
b0 I
b0 a
b0 ;
b0 c
b0 d
b0 D
b0 Y
b0 G
b0 (
b0 `
b0 N
b0 A
b0 O
b0 V
b0 @
b0 W
b0 _
b0 ^
b0 ?
b0 b
bx0 S
bx0 <
bx0 T
bx0 X
bx0 B
bx0 Q
0/
0$
01
0&
00
0%
0.
0#
02
0'
13
b0 5
17
1!
#500000
07
0!
#502000
08
0"
#750000
bx a
bx ;
bx c
bx0 V
bx0 @
bx0 W
bx0 _
b0 4
17
1!
#1000000
07
0!
#1250000
17
1!
#1500000
07
0!
#1750000
17
1!
#2000000
07
0!
#2250000
17
1!
#2500000
03
b1 6
07
0!
1:
1*
#2750000
bx d
bx D
bx Y
bx00 X
bx00 B
bx00 Q
b1010101010101010101 K
b1010101010101010101 =
b1010101010101010101 L
b1010 S
b1010 <
b1010 T
1/
1$
12
1'
11
1&
10
1%
1.
1#
b1 4
b1 5
17
1!
#3000000
07
0!
0:
0*
#3250000
1H
1+
b1010 d
b1010 D
b1010 Y
b101010101010101010 P
b101010101010101010 C
b101010101010101010 I
b1010 a
b1010 ;
b1010 c
b10 4
b1010101010101010101 N
b1010101010101010101 A
b1010101010101010101 O
b1010 V
b1010 @
b1010 W
b1010 _
17
1!
#3500000
07
0!
#3750000
b11 4
17
1!
#4000000
07
0!
#4250000
b100 4
17
1!
#4500000
07
0!
#4750000
b101 4
17
1!
#5000000
07
0!
#5250000
b110 4
17
1!
#5500000
07
0!
#5750000
b111 4
17
1!
#6000000
07
0!
#6250000
b1000 4
17
1!
#6500000
07
0!
#6750000
b1001 4
17
1!
#7000000
07
0!
#7250000
b1010 4
17
1!
#7500000
07
0!
#7750000
b1011 4
17
1!
#8000000
07
0!
#8250000
b1100 4
17
1!
#8500000
07
0!
#8750000
b1101 4
17
1!
#9000000
07
0!
#9250000
b1110 4
17
1!
#9500000
07
0!
#9750000
b1111 4
17
1!
#10000000
07
0!
#10250000
b10000 4
17
1!
#10500000
07
0!
#10750000
b10001 4
17
1!
#11000000
07
0!
#11250000
b10010 4
17
1!
#11500000
07
0!
#11750000
b10011 4
17
1!
#12000000
07
0!
#12250000
b10100 4
17
1!
#12500000
07
0!
#12750000
b10101 4
17
1!
#13000000
07
0!
#13250000
b10110 4
17
1!
#13500000
07
0!
#13750000
b10111 4
17
1!
#14000000
07
0!
#14250000
b11000 4
17
1!
#14500000
07
0!
#14750000
b11001 4
17
1!
#15000000
07
0!
#15250000
b11010 4
17
1!
#15500000
07
0!
#15750000
b11011 4
17
1!
#16000000
07
0!
#16250000
b11100 4
17
1!
#16500000
07
0!
#16750000
b11101 4
17
1!
#17000000
07
0!
#17250000
b11110 4
17
1!
#17500000
07
0!
#17750000
b11111 4
17
1!
#18000000
07
0!
#18250000
13
b10 6
b100000 4
17
1!
#18500000
07
0!
#18750000
b0 d
b0 D
b0 Y
b10100 X
b10100 B
b10100 Q
0/
0$
02
0'
b0 4
b10 5
17
1!
#19000000
07
0!
#19250000
17
1!
#19500000
07
0!
#19750000
17
1!
#20000000
07
0!
#20250000
17
1!
#20500000
07
0!
#20750000
17
1!
#21000000
07
0!
#21250000
17
1!
#21500000
07
0!
#21750000
17
1!
#22000000
07
0!
#22250000
17
1!
#22500000
07
0!
#22750000
17
1!
#23000000
07
0!
#23250000
17
1!
#23500000
07
0!
#23750000
17
1!
#24000000
07
0!
#24250000
17
1!
#24500000
07
0!
#24750000
17
1!
#25000000
b0 6
07
0!
19
1)
#25250000
b101010101010101010 K
b101010101010101010 =
b101010101010101010 L
b10100 S
b10100 <
b10100 T
01
0&
00
0%
0.
0#
b0 5
17
1!
#25500000
07
0!
09
0)
#25750000
0H
0+
b10101010101010101 K
b10101010101010101 =
b10101010101010101 L
b10100 a
b10100 ;
b10100 c
b10101010101010101 P
b10101010101010101 C
b10101010101010101 I
b10100 V
b10100 @
b10100 W
b10100 _
b101010101010101010 N
b101010101010101010 A
b101010101010101010 O
17
1!
#26000000
07
0!
#26250000
1H
1+
b1010101010101010 K
b1010101010101010 =
b1010101010101010 L
b1010101010101010 P
b1010101010101010 C
b1010101010101010 I
b10101010101010101 N
b10101010101010101 A
b10101010101010101 O
17
1!
#26500000
07
0!
#26750000
0H
0+
b101010101010101 K
b101010101010101 =
b101010101010101 L
b101010101010101 P
b101010101010101 C
b101010101010101 I
b1010101010101010 N
b1010101010101010 A
b1010101010101010 O
17
1!
#27000000
07
0!
#27250000
1H
1+
b10101010101010 K
b10101010101010 =
b10101010101010 L
b10101010101010 P
b10101010101010 C
b10101010101010 I
b101010101010101 N
b101010101010101 A
b101010101010101 O
17
1!
#27500000
07
0!
#27750000
0H
0+
b1010101010101 K
b1010101010101 =
b1010101010101 L
b1010101010101 P
b1010101010101 C
b1010101010101 I
b10101010101010 N
b10101010101010 A
b10101010101010 O
17
1!
#28000000
07
0!
#28250000
1H
1+
b101010101010 K
b101010101010 =
b101010101010 L
b101010101010 P
b101010101010 C
b101010101010 I
b1010101010101 N
b1010101010101 A
b1010101010101 O
17
1!
#28500000
07
0!
#28750000
0H
0+
b10101010101 K
b10101010101 =
b10101010101 L
b10101010101 P
b10101010101 C
b10101010101 I
b101010101010 N
b101010101010 A
b101010101010 O
17
1!
#29000000
07
0!
#29250000
1H
1+
b1010101010 K
b1010101010 =
b1010101010 L
b1010101010 P
b1010101010 C
b1010101010 I
b10101010101 N
b10101010101 A
b10101010101 O
17
1!
#29500000
07
0!
#29750000
0H
0+
b101010101 K
b101010101 =
b101010101 L
b101010101 P
b101010101 C
b101010101 I
b1010101010 N
b1010101010 A
b1010101010 O
17
1!
#30000000
07
0!
#30250000
1H
1+
b10101010 K
b10101010 =
b10101010 L
b10101010 P
b10101010 C
b10101010 I
b101010101 N
b101010101 A
b101010101 O
17
1!
#30500000
07
0!
#30750000
0H
0+
b1010101 K
b1010101 =
b1010101 L
b1010101 P
b1010101 C
b1010101 I
b10101010 N
b10101010 A
b10101010 O
17
1!
#31000000
07
0!
#31250000
1H
1+
b101010 K
b101010 =
b101010 L
b101010 P
b101010 C
b101010 I
b1010101 N
b1010101 A
b1010101 O
17
1!
#31500000
07
0!
#31750000
0H
0+
b10101 K
b10101 =
b10101 L
b10101 P
b10101 C
b10101 I
b101010 N
b101010 A
b101010 O
17
1!
#32000000
07
0!
#32250000
1H
1+
b1010 K
b1010 =
b1010 L
b1010 P
b1010 C
b1010 I
b10101 N
b10101 A
b10101 O
17
1!
#32500000
07
0!
#32750000
0H
0+
b101 K
b101 =
b101 L
b101 P
b101 C
b101 I
b1010 N
b1010 A
b1010 O
17
1!
#33000000
07
0!
#33250000
1H
1+
b10 K
b10 =
b10 L
b10 P
b10 C
b10 I
b101 N
b101 A
b101 O
17
1!
#33500000
07
0!
#33750000
0H
0+
b1 K
b1 =
b1 L
b1 P
b1 C
b1 I
b10 N
b10 A
b10 O
17
1!
#34000000
07
0!
#34250000
1H
1+
b0 K
b0 =
b0 L
b0 P
b0 C
b0 I
b1 N
b1 A
b1 O
17
1!
#34500000
07
0!
#34750000
0H
0+
b0 N
b0 A
b0 O
17
1!
