DataPath.v
module DataPath
(
	input wire b_sel,
	input wire a_sel,
	input wire add_sel,
	input wire prod_sel,
	input wire [31:0]Data_A,
	input wire [31:0]Data_B,
	input wire Shift_Enable,
	input wire Clock,
	input wire Reset,
	output reg [63:0]Prod,
	output wire oB_LSB

);

//-------------PARA B-----------------//
wire [31:0]Mux_B_Out;
wire [31:0]Reg_B_Out;
wire [31:0]Shifted_B;


assign	oB_LSB= Reg_B_Out[0];
assign  Shifted_B = Reg_B_Out >>1;
MUX #(32) Mux_B
(
	.Select(b_sel),
	.Data_A(Shifted_B),
	.Data_B(Data_B),
	.Out(Mux_B_Out)
);

FFD #(32) Reg_B
(
	.Clock(Clock),
	.Reset(Reset),
	.Enable(1),
	.D(Mux_B_Out),
	.Q(Reg_B_Out)
	
);

/*Shift_Register_Right Shift_B
(	.Clock(Clock),
	.Data(Reg_B_Out),
	.Enable(Shift_Enable),
	.Shifted_Data(Shifted_B)
);*/

//--------PARA A----------//
wire [63:0]Mux_A_Out;
wire [63:0]Reg_A_Out;
wire [63:0]Shifted_A;
wire [63:0]A_64_Bits;
assign  Shifted_A = {32'b0,Reg_A_Out} <<1;
assign  A_64_Bits = {32'b0,Data_A} ;
MUX #(64) Mux_A
(
	.Select(a_sel),
	.Data_A(Shifted_A),
	.Data_B(A_64_Bits),
	.Out(Mux_A_Out)
);

FFD #(64) Reg_A
(
	.Clock(Clock),
	.Reset(Reset),
	.Enable(1),
	.D(Mux_A_Out),
	.Q(Reg_A_Out)
	
);
/*
Shift_Register_Left Shift_A
(	.Clock(Clock),
	.Data(Reg_A_Out),
	.Enable(Shift_Enable),
	.Shifted_Data(Shifted_A)
);*/

//--------PARA EL PRODUCTO------------//
wire [63:0]Mux_Prod_Out;
wire [63:0]Add_Out;
wire [63:0]Sum_Prod;

MUX #(64) Mux_Prod1
(
	.Select(prod_sel),
	.Data_A(Sum_Prod),
	.Data_B(64'b0),
	.Out(Mux_Prod_Out)
);

wire [63:0]Product;
always @ (Product)
	Prod=Product;
	
FFD #(64) Reg_Prod
(
	.Clock(Clock),
	.Reset(Reset),
	.Enable(1),
	.D(Mux_Prod_Out),
	.Q(Product)
);

ADDER Adder_Prod
(

	.Data_A(Reg_A_Out),
	.Data_B(Product),
	.Result(Add_Out)
);

MUX #(64) Mux_Prod0
(
	.Select(add_sel),
	.Data_A(Add_Out),
	.Data_B(Product),
	.Out(Sum_Prod)
);
endmodule


///////////////////MUX//////////////////
module MUX #(parameter SIZE=32)
(
	input wire Select,
	input wire [SIZE-1:0]Data_B,
	input wire [SIZE-1:0]Data_A,
	output reg [SIZE-1:0] Out
);


always @(*)
	begin
		if(Select==1)
			Out<=Data_A;
		else if (Select==0)
			Out<=Data_B;
	end

endmodule

///////////////REGISTER///////////////
module FFD # ( parameter SIZE=32 )
(
	input wire				Clock,
	input wire				Reset,
	input wire				Enable,
	input wire [SIZE-1:0]	D,
	output reg [SIZE-1:0]	Q
);


always @ (posedge Clock) 
begin
	if ( Reset )
		Q <= 0;
	else
	begin	
		if (Enable) 
			Q <= D; 
	end	
 
end

endmodule

////////////////SHIFT REGISTER RIGHT//////////
module Shift_Register_Right
(	input wire Clock,
	input wire [31:0]Data,
	input wire Enable,
	output reg [31:0]Shifted_Data
);
	reg newClock;
initial
  begin 
 
  newClock =0;
  end
  always
	begin
   # 125 newClock  =1;
   # 125 newClock  =0;
   
	end
	always @(  posedge  newClock)
	if(Enable)
		begin
			Shifted_Data = Data>>1;
		end
	else
		begin
			Shifted_Data = Data;
		end
endmodule

////////////SHIFT REGISTER LEFT//////////////
module Shift_Register_Left
(	input wire Clock,
	input wire [31:0]Data,
	input wire Enable,
	output reg [31:0]Shifted_Data
);
reg newClock;
initial
  begin 
 
  newClock =0;
  end
  always
	begin
   # 125 newClock  =1;
   # 125 newClock  =0;
   
	end
always @(posedge newClock)
	if(Enable)
		begin
			Shifted_Data = Data<<1;
		end
	else
		begin
			Shifted_Data = Data;
		end
endmodule


////////////ADDER///////////////////////////
module ADDER
(
	input wire [63:0]Data_A,
	input wire [63:0]Data_B,
	output reg [63:0]Result
);

	always @(*)
		begin
			Result <= Data_B + Data_A;
		end
endmodule

generator.v
module probador(clk,rst,acknowledge,validdata);
output clk,rst,acknowledge,validdata;

reloj r1(clk);
reset rs(rst);
ack a1(acknowledge);
valid d1(validdata);
endmodule
//generacion del reloj
module reloj(clk);
output clk;
reg clk;  
initial
  begin 
 
  clk =0;
  end
  always
	begin
   #250 clk =1;
   #250 clk =0;
   
	end
endmodule
//generacion del reset
module reset (rst);
output rst;
reg rst;
initial
	begin
	 rst=0;
	#2 rst=~rst;
	#600 rst=~rst;
	end
endmodule

module ack (acknowledge);
output acknowledge;
reg acknowledge;
initial
	begin
	
	 acknowledge=0;
	#20000 acknowledge=~acknowledge;
	#400 acknowledge=~acknowledge;
	end
endmodule

module valid (validdata);
output validdata;
reg validdata;
initial
	begin
	
	validdata=0;
	#1000 validdata=~validdata;
	#500 validdata=~validdata;
	end
endmodule

controlMachine.v

`define STATE_IDLE 0
`define STATE_CALC 1
`define STATE_DONE 2





//------------------------------------------------



module control_Machine
  (
    input wire Clock,
    input wire Reset,
    input wire iLSB,   
    input wire iValid_Data,
    input wire iAck,
    output reg oShift,
    output reg  oA_Sel,
    output reg oB_Sel,
    output reg oProduct_Sel,
    output reg oAdd_Sel
  );
  //Registros  internos del controlador
  
  reg [5:0] rCounter;
  reg [1:0]rCurrentState;
  reg  [1:0]rNextState;
  reg rCountReset;
  reg firstBit;

  //Next State and delay logic
  always @ ( posedge Clock )
    if (Reset)
      begin
        rCurrentState = `STATE_IDLE;
        rCountReset <=1'b1;
        firstBit <=1'b0;
        
       
      end
  else
		begin
      rCurrentState <= rNextState;
      if(rCountReset)
      begin
      rCounter<= 6'd0;
      end
      
      else
      
     begin
     rCounter<=  rCounter + 6'd1;
     end
		end
    

  //----------------------------------------------
  //Current state and output logic
  always @ ( * )
    begin
      case (rCurrentState)
        //------------------------------------------
        `STATE_IDLE:
          begin
          rCountReset=1'b1;
          oShift=1'b0;
         oA_Sel=1'b0;
         oB_Sel=1'b0;
         oProduct_Sel=1'b0;
         oAdd_Sel=1'b0;
         if(iValid_Data)
			begin
            rNextState = `STATE_CALC;
            rCountReset=1'b0;
           firstBit=1'b1;
            end
          else
			begin
			rNextState= `STATE_IDLE;
			end
          end
//------------------------------------------
/*

*/
      `STATE_CALC:
        begin
       /* if(firstBit)
        begin
        oA_Sel=1'b0;
         oB_Sel=1'b0;
            oProduct_Sel=1'b0;
            firstBit=1'b0;
        end
        else
        begin*/
         oA_Sel=1'b1;
         oB_Sel=1'b1;
            oProduct_Sel=1'b1;
           // end
         if(iLSB)
         begin
           oShift=1'b1;
           oAdd_Sel=1'b0;
           end
           else
           begin
           oShift=1'b1;
           oAdd_Sel=1'b1;
           end
           
       if(rCounter<6'd32)
       begin
       rNextState=`STATE_CALC;
       end    
       else
       begin 
        rNextState=`STATE_DONE;
         rCountReset=1'b1;
       end
          
          
          
          
        end
//------------------------------------------
/*

  */
      `STATE_DONE:
        begin
          rCounter= 6'd0;
          oShift=1'b0;
         oAdd_Sel=1'b0;
          if ( iAck)
            rNextState = `STATE_IDLE;
          else
            rNextState = `STATE_DONE;
        end

//------------------------------------------
        
 
        default:
          begin
            rNextState = `STATE_IDLE;
          end
        //------------------------------------------
      endcase
    end
endmodule

testbench.v
`timescale 1ns/1ps
`include "controlMachine.v"
`include "generator.v"
`include "DataPath.v"
module BancoPruebas;
wire Clock,Reset,wAck,wValidData;
wire oShift,oA_Sel,oB_Sel, oProduct_Sel,oAdd_Sel, wiLSB;
reg [31:0] dataA=32'd4294967295;
reg [31:0] dataB=32'd4294967295;
wire [63:0] product;

control_Machine control1(.Clock(Clock),.Reset(Reset),.iLSB(wiLSB),.iValid_Data(wValidData),.iAck(wAck),.oShift(oShift),.oA_Sel(oA_Sel),.oB_Sel(oB_Sel),.oProduct_Sel(oProduct_Sel),.oAdd_Sel(oAdd_Sel));
probador p1(.clk(Clock),.rst(Reset),.acknowledge(wAck),.validdata(wValidData));

DataPath data1(.add_sel(oAdd_Sel),
	.b_sel(oB_Sel), .a_sel(oA_Sel), .prod_sel(oProduct_Sel), .Data_A(dataA), .Data_B(dataB), .Shift_Enable(oShift), .Clock(Clock), .Reset(Reset), .Prod(product), .oB_LSB(wiLSB));



 initial 
  begin
    $dumpfile("signals.vcd");
    $dumpvars;
	#27000;
	dataA=32'd0; dataB=32'd4294967295;
	#27000;
	dataA=32'd10000; dataB=32'd4500;
    #70000 ;
    $display ("Test finished");
    $finish;
   
  end
endmodule

signals.vcd
$date
	Thu May 14 17:01:19 2015
$end
$version
	Icarus Verilog
$end
$timescale
	1ps
$end
$scope module BancoPruebas $end
$var wire 1 ! Clock $end
$var wire 1 " Reset $end
$var wire 1 # oA_Sel $end
$var wire 1 $ oAdd_Sel $end
$var wire 1 % oB_Sel $end
$var wire 1 & oProduct_Sel $end
$var wire 1 ' oShift $end
$var wire 64 ( product [63:0] $end
$var wire 1 ) wAck $end
$var wire 1 * wValidData $end
$var wire 1 + wiLSB $end
$var reg 32 , dataA [31:0] $end
$var reg 32 - dataB [31:0] $end
$scope module control1 $end
$var wire 1 ! Clock $end
$var wire 1 " Reset $end
$var wire 1 ) iAck $end
$var wire 1 + iLSB $end
$var wire 1 * iValid_Data $end
$var reg 1 . firstBit $end
$var reg 1 / oA_Sel $end
$var reg 1 0 oAdd_Sel $end
$var reg 1 1 oB_Sel $end
$var reg 1 2 oProduct_Sel $end
$var reg 1 3 oShift $end
$var reg 1 4 rCountReset $end
$var reg 6 5 rCounter [5:0] $end
$var reg 2 6 rCurrentState [1:0] $end
$var reg 2 7 rNextState [1:0] $end
$upscope $end
$scope module p1 $end
$var wire 1 ) acknowledge $end
$var wire 1 ! clk $end
$var wire 1 " rst $end
$var wire 1 * validdata $end
$scope module r1 $end
$var reg 1 8 clk $end
$upscope $end
$scope module rs $end
$var reg 1 9 rst $end
$upscope $end
$scope module a1 $end
$var reg 1 : acknowledge $end
$upscope $end
$scope module d1 $end
$var reg 1 ; validdata $end
$upscope $end
$upscope $end
$scope module data1 $end
$var wire 64 < A_64_Bits [63:0] $end
$var wire 64 = Add_Out [63:0] $end
$var wire 1 ! Clock $end
$var wire 32 > Data_A [31:0] $end
$var wire 32 ? Data_B [31:0] $end
$var wire 64 @ Mux_A_Out [63:0] $end
$var wire 32 A Mux_B_Out [31:0] $end
$var wire 64 B Mux_Prod_Out [63:0] $end
$var wire 64 C Product [63:0] $end
$var wire 64 D Reg_A_Out [63:0] $end
$var wire 32 E Reg_B_Out [31:0] $end
$var wire 1 " Reset $end
$var wire 1 ' Shift_Enable $end
$var wire 64 F Shifted_A [63:0] $end
$var wire 32 G Shifted_B [31:0] $end
$var wire 64 H Sum_Prod [63:0] $end
$var wire 1 # a_sel $end
$var wire 1 $ add_sel $end
$var wire 1 % b_sel $end
$var wire 1 + oB_LSB $end
$var wire 1 & prod_sel $end
$var reg 64 I Prod [63:0] $end
$scope module Mux_B $end
$var wire 32 J Data_A [31:0] $end
$var wire 32 K Data_B [31:0] $end
$var wire 1 % Select $end
$var reg 32 L Out [31:0] $end
$upscope $end
$scope module Reg_B $end
$var wire 1 ! Clock $end
$var wire 32 M D [31:0] $end
$var wire 1 N Enable $end
$var wire 1 " Reset $end
$var reg 32 O Q [31:0] $end
$upscope $end
$scope module Mux_A $end
$var wire 64 P Data_A [63:0] $end
$var wire 64 Q Data_B [63:0] $end
$var wire 1 # Select $end
$var reg 64 R Out [63:0] $end
$upscope $end
$scope module Reg_A $end
$var wire 1 ! Clock $end
$var wire 64 S D [63:0] $end
$var wire 1 T Enable $end
$var wire 1 " Reset $end
$var reg 64 U Q [63:0] $end
$upscope $end
$scope module Mux_Prod1 $end
$var wire 64 V Data_A [63:0] $end
$var wire 64 W Data_B [63:0] $end
$var wire 1 & Select $end
$var reg 64 X Out [63:0] $end
$upscope $end
$scope module Reg_Prod $end
$var wire 1 ! Clock $end
$var wire 64 Y D [63:0] $end
$var wire 1 Z Enable $end
$var wire 1 " Reset $end
$var reg 64 [ Q [63:0] $end
$upscope $end
$scope module Adder_Prod $end
$var wire 64 \ Data_A [63:0] $end
$var wire 64 ] Data_B [63:0] $end
$var reg 64 ^ Result [63:0] $end
$upscope $end
$scope module Mux_Prod0 $end
$var wire 64 _ Data_A [63:0] $end
$var wire 64 ` Data_B [63:0] $end
$var wire 1 $ Select $end
$var reg 64 a Out [63:0] $end
$upscope $end
$upscope $end
$upscope $end
$scope module Shift_Register_Left $end
$var wire 1 b Clock $end
$var wire 32 c Data [31:0] $end
$var wire 1 d Enable $end
$var reg 32 e Shifted_Data [31:0] $end
$var reg 1 f newClock $end
$upscope $end
$scope module Shift_Register_Right $end
$var wire 1 g Clock $end
$var wire 32 h Data [31:0] $end
$var wire 1 i Enable $end
$var reg 32 j Shifted_Data [31:0] $end
$var reg 1 k newClock $end
$upscope $end
$enddefinitions $end
#0
$dumpvars
0k
bx j
zi
bz h
zg
0f
bx e
zd
bz c
zb
bx a
bx `
bx _
bx ^
bx ]
bx \
bx [
1Z
bx Y
bx X
b0 W
bx V
bx U
1T
bx S
bx R
b11111111111111111111111111111111 Q
bx0 P
bx O
1N
bx M
bx L
b11111111111111111111111111111111 K
b0xxxxxxxxxxxxxxxxxxxxxxxxxxxxxxx J
bx I
bx H
b0xxxxxxxxxxxxxxxxxxxxxxxxxxxxxxx G
bx0 F
bx E
bx D
bx C
bx B
bx A
bx @
b11111111111111111111111111111111 ?
b11111111111111111111111111111111 >
bx =
b11111111111111111111111111111111 <
0;
0:
09
08
b0 7
bx 6
bx 5
x4
x3
x2
x1
x0
x/
x.
b11111111111111111111111111111111 -
b11111111111111111111111111111111 ,
x+
0*
0)
bx (
x'
x&
x%
x$
x#
0"
0!
$end
#2000
19
1"
#125000
bz j
bz e
1k
1f
#250000
b0 a
b0 H
b0 V
b0 ^
b0 =
b0 _
b0 F
b0 P
b0 G
b0 J
0+
b0 I
b0 (
b0 X
b0 B
b0 Y
b11111111111111111111111111111111 L
b11111111111111111111111111111111 A
b11111111111111111111111111111111 M
b11111111111111111111111111111111 R
b11111111111111111111111111111111 @
b11111111111111111111111111111111 S
0.
b0 O
b0 E
b0 U
b0 D
b0 \
b0 [
b0 C
b0 ]
b0 `
00
0$
02
0&
01
0%
0/
0#
03
0'
14
b0 6
0k
0f
18
1!
#375000
1k
1f
#500000
0k
0f
08
0!
#502000
09
0"
#625000
1k
1f
#750000
b11111111111111111111111111111111 ^
b11111111111111111111111111111111 =
b11111111111111111111111111111111 _
b111111111111111111111111111111110 F
b111111111111111111111111111111110 P
b1111111111111111111111111111111 G
b1111111111111111111111111111111 J
1+
b11111111111111111111111111111111 U
b11111111111111111111111111111111 D
b11111111111111111111111111111111 \
b11111111111111111111111111111111 O
b11111111111111111111111111111111 E
b0 5
0k
0f
18
1!
#875000
1k
1f
#1000000
0k
0f
08
0!
#1125000
1k
1f
#1250000
0k
0f
18
1!
#1375000
1k
1f
#1500000
0k
0f
08
0!
#1625000
1k
1f
#1750000
0k
0f
18
1!
#1875000
1k
1f
#2000000
0k
0f
08
0!
#2125000
1k
1f
#2250000
0k
0f
18
1!
#2375000
1k
1f
#2500000
1.
04
b1 7
0k
0f
08
0!
1;
1*
#2625000
1k
1f
#2750000
b11111111111111111111111111111111 X
b11111111111111111111111111111111 B
b11111111111111111111111111111111 Y
b11111111111111111111111111111111 a
b11111111111111111111111111111111 H
b11111111111111111111111111111111 V
b1111111111111111111111111111111 L
b1111111111111111111111111111111 A
b1111111111111111111111111111111 M
b111111111111111111111111111111110 R
b111111111111111111111111111111110 @
b111111111111111111111111111111110 S
10
1$
13
1'
12
1&
11
1%
1/
1#
b1 5
b1 6
0k
0f
18
1!
#2875000
1k
1f
#3000000
0k
0f
08
0!
0;
0*
#3125000
1k
1f
#3250000
b1011111111111111111111111111111101 X
b1011111111111111111111111111111101 B
b1011111111111111111111111111111101 Y
b1011111111111111111111111111111101 a
b1011111111111111111111111111111101 H
b1011111111111111111111111111111101 V
b1111111111111111111111111111111100 R
b1111111111111111111111111111111100 @
b1111111111111111111111111111111100 S
b111111111111111111111111111111 L
b111111111111111111111111111111 A
b111111111111111111111111111111 M
b1011111111111111111111111111111101 ^
b1011111111111111111111111111111101 =
b1011111111111111111111111111111101 _
b1111111111111111111111111111111100 F
b1111111111111111111111111111111100 P
b111111111111111111111111111111 G
b111111111111111111111111111111 J
b11111111111111111111111111111111 I
b11111111111111111111111111111111 (
b10 5
b1111111111111111111111111111111 O
b1111111111111111111111111111111 E
b111111111111111111111111111111110 U
b111111111111111111111111111111110 D
b111111111111111111111111111111110 \
b11111111111111111111111111111111 [
b11111111111111111111111111111111 C
b11111111111111111111111111111111 ]
b11111111111111111111111111111111 `
0k
0f
18
1!
#3375000
1k
1f
#3500000
0k
0f
08
0!
#3625000
1k
1f
#3750000
b11011111111111111111111111111111001 X
b11011111111111111111111111111111001 B
b11011111111111111111111111111111001 Y
b11011111111111111111111111111111001 a
b11011111111111111111111111111111001 H
b11011111111111111111111111111111001 V
b11111111111111111111111111111111000 R
b11111111111111111111111111111111000 @
b11111111111111111111111111111111000 S
b11111111111111111111111111111 L
b11111111111111111111111111111 A
b11111111111111111111111111111 M
b11011111111111111111111111111111001 ^
b11011111111111111111111111111111001 =
b11011111111111111111111111111111001 _
b11111111111111111111111111111111000 F
b11111111111111111111111111111111000 P
b1011111111111111111111111111111101 I
b1011111111111111111111111111111101 (
b11111111111111111111111111111 G
b11111111111111111111111111111 J
b1011111111111111111111111111111101 [
b1011111111111111111111111111111101 C
b1011111111111111111111111111111101 ]
b1011111111111111111111111111111101 `
b1111111111111111111111111111111100 U
b1111111111111111111111111111111100 D
b1111111111111111111111111111111100 \
b111111111111111111111111111111 O
b111111111111111111111111111111 E
b11 5
0k
0f
18
1!
#3875000
1k
1f
#4000000
0k
0f
08
0!
#4125000
1k
1f
#4250000
b111011111111111111111111111111110001 X
b111011111111111111111111111111110001 B
b111011111111111111111111111111110001 Y
b111011111111111111111111111111110001 a
b111011111111111111111111111111110001 H
b111011111111111111111111111111110001 V
b111111111111111111111111111111110000 R
b111111111111111111111111111111110000 @
b111111111111111111111111111111110000 S
b1111111111111111111111111111 L
b1111111111111111111111111111 A
b1111111111111111111111111111 M
b111011111111111111111111111111110001 ^
b111011111111111111111111111111110001 =
b111011111111111111111111111111110001 _
b111111111111111111111111111111110000 F
b111111111111111111111111111111110000 P
b1111111111111111111111111111 G
b1111111111111111111111111111 J
b11011111111111111111111111111111001 I
b11011111111111111111111111111111001 (
b100 5
b11111111111111111111111111111 O
b11111111111111111111111111111 E
b11111111111111111111111111111111000 U
b11111111111111111111111111111111000 D
b11111111111111111111111111111111000 \
b11011111111111111111111111111111001 [
b11011111111111111111111111111111001 C
b11011111111111111111111111111111001 ]
b11011111111111111111111111111111001 `
0k
0f
18
1!
#4375000
1k
1f
#4500000
0k
0f
08
0!
#4625000
1k
1f
#4750000
b1111011111111111111111111111111100001 X
b1111011111111111111111111111111100001 B
b1111011111111111111111111111111100001 Y
b1111011111111111111111111111111100001 a
b1111011111111111111111111111111100001 H
b1111011111111111111111111111111100001 V
b1111111111111111111111111111111100000 R
b1111111111111111111111111111111100000 @
b1111111111111111111111111111111100000 S
b111111111111111111111111111 L
b111111111111111111111111111 A
b111111111111111111111111111 M
b1111011111111111111111111111111100001 ^
b1111011111111111111111111111111100001 =
b1111011111111111111111111111111100001 _
b1111111111111111111111111111111100000 F
b1111111111111111111111111111111100000 P
b111011111111111111111111111111110001 I
b111011111111111111111111111111110001 (
b111111111111111111111111111 G
b111111111111111111111111111 J
b111011111111111111111111111111110001 [
b111011111111111111111111111111110001 C
b111011111111111111111111111111110001 ]
b111011111111111111111111111111110001 `
b111111111111111111111111111111110000 U
b111111111111111111111111111111110000 D
b111111111111111111111111111111110000 \
b1111111111111111111111111111 O
b1111111111111111111111111111 E
b101 5
0k
0f
18
1!
#4875000
1k
1f
#5000000
0k
0f
08
0!
#5125000
1k
1f
#5250000
b11111011111111111111111111111111000001 X
b11111011111111111111111111111111000001 B
b11111011111111111111111111111111000001 Y
b11111011111111111111111111111111000001 a
b11111011111111111111111111111111000001 H
b11111011111111111111111111111111000001 V
b11111111111111111111111111111111000000 R
b11111111111111111111111111111111000000 @
b11111111111111111111111111111111000000 S
b11111111111111111111111111 L
b11111111111111111111111111 A
b11111111111111111111111111 M
b11111011111111111111111111111111000001 ^
b11111011111111111111111111111111000001 =
b11111011111111111111111111111111000001 _
b11111111111111111111111111111111000000 F
b11111111111111111111111111111111000000 P
b11111111111111111111111111 G
b11111111111111111111111111 J
b1111011111111111111111111111111100001 I
b1111011111111111111111111111111100001 (
b110 5
b111111111111111111111111111 O
b111111111111111111111111111 E
b1111111111111111111111111111111100000 U
b1111111111111111111111111111111100000 D
b1111111111111111111111111111111100000 \
b1111011111111111111111111111111100001 [
b1111011111111111111111111111111100001 C
b1111011111111111111111111111111100001 ]
b1111011111111111111111111111111100001 `
0k
0f
18
1!
#5375000
1k
1f
#5500000
0k
0f
08
0!
#5625000
1k
1f
#5750000
b111111011111111111111111111111110000001 X
b111111011111111111111111111111110000001 B
b111111011111111111111111111111110000001 Y
b111111011111111111111111111111110000001 a
b111111011111111111111111111111110000001 H
b111111011111111111111111111111110000001 V
b111111111111111111111111111111110000000 R
b111111111111111111111111111111110000000 @
b111111111111111111111111111111110000000 S
b1111111111111111111111111 L
b1111111111111111111111111 A
b1111111111111111111111111 M
b111111011111111111111111111111110000001 ^
b111111011111111111111111111111110000001 =
b111111011111111111111111111111110000001 _
b111111111111111111111111111111110000000 F
b111111111111111111111111111111110000000 P
b11111011111111111111111111111111000001 I
b11111011111111111111111111111111000001 (
b1111111111111111111111111 G
b1111111111111111111111111 J
b11111011111111111111111111111111000001 [
b11111011111111111111111111111111000001 C
b11111011111111111111111111111111000001 ]
b11111011111111111111111111111111000001 `
b11111111111111111111111111111111000000 U
b11111111111111111111111111111111000000 D
b11111111111111111111111111111111000000 \
b11111111111111111111111111 O
b11111111111111111111111111 E
b111 5
0k
0f
18
1!
#5875000
1k
1f
#6000000
0k
0f
08
0!
#6125000
1k
1f
#6250000
b1111111011111111111111111111111100000001 X
b1111111011111111111111111111111100000001 B
b1111111011111111111111111111111100000001 Y
b1111111011111111111111111111111100000001 a
b1111111011111111111111111111111100000001 H
b1111111011111111111111111111111100000001 V
b1111111111111111111111111111111100000000 R
b1111111111111111111111111111111100000000 @
b1111111111111111111111111111111100000000 S
b111111111111111111111111 L
b111111111111111111111111 A
b111111111111111111111111 M
b1111111011111111111111111111111100000001 ^
b1111111011111111111111111111111100000001 =
b1111111011111111111111111111111100000001 _
b1111111111111111111111111111111100000000 F
b1111111111111111111111111111111100000000 P
b111111111111111111111111 G
b111111111111111111111111 J
b111111011111111111111111111111110000001 I
b111111011111111111111111111111110000001 (
b1000 5
b1111111111111111111111111 O
b1111111111111111111111111 E
b111111111111111111111111111111110000000 U
b111111111111111111111111111111110000000 D
b111111111111111111111111111111110000000 \
b111111011111111111111111111111110000001 [
b111111011111111111111111111111110000001 C
b111111011111111111111111111111110000001 ]
b111111011111111111111111111111110000001 `
0k
0f
18
1!
#6375000
1k
1f
#6500000
0k
0f
08
0!
#6625000
1k
1f
#6750000
b11111111011111111111111111111111000000001 X
b11111111011111111111111111111111000000001 B
b11111111011111111111111111111111000000001 Y
b11111111011111111111111111111111000000001 a
b11111111011111111111111111111111000000001 H
b11111111011111111111111111111111000000001 V
b11111111111111111111111111111111000000000 R
b11111111111111111111111111111111000000000 @
b11111111111111111111111111111111000000000 S
b11111111111111111111111 L
b11111111111111111111111 A
b11111111111111111111111 M
b11111111011111111111111111111111000000001 ^
b11111111011111111111111111111111000000001 =
b11111111011111111111111111111111000000001 _
b11111111111111111111111111111111000000000 F
b11111111111111111111111111111111000000000 P
b1111111011111111111111111111111100000001 I
b1111111011111111111111111111111100000001 (
b11111111111111111111111 G
b11111111111111111111111 J
b1111111011111111111111111111111100000001 [
b1111111011111111111111111111111100000001 C
b1111111011111111111111111111111100000001 ]
b1111111011111111111111111111111100000001 `
b1111111111111111111111111111111100000000 U
b1111111111111111111111111111111100000000 D
b1111111111111111111111111111111100000000 \
b111111111111111111111111 O
b111111111111111111111111 E
b1001 5
0k
0f
18
1!
#6875000
1k
1f
#7000000
0k
0f
08
0!
#7125000
1k
1f
#7250000
b111111111011111111111111111111110000000001 X
b111111111011111111111111111111110000000001 B
b111111111011111111111111111111110000000001 Y
b111111111011111111111111111111110000000001 a
b111111111011111111111111111111110000000001 H
b111111111011111111111111111111110000000001 V
b111111111111111111111111111111110000000000 R
b111111111111111111111111111111110000000000 @
b111111111111111111111111111111110000000000 S
b1111111111111111111111 L
b1111111111111111111111 A
b1111111111111111111111 M
b111111111011111111111111111111110000000001 ^
b111111111011111111111111111111110000000001 =
b111111111011111111111111111111110000000001 _
b111111111111111111111111111111110000000000 F
b111111111111111111111111111111110000000000 P
b1111111111111111111111 G
b1111111111111111111111 J
b11111111011111111111111111111111000000001 I
b11111111011111111111111111111111000000001 (
b1010 5
b11111111111111111111111 O
b11111111111111111111111 E
b11111111111111111111111111111111000000000 U
b11111111111111111111111111111111000000000 D
b11111111111111111111111111111111000000000 \
b11111111011111111111111111111111000000001 [
b11111111011111111111111111111111000000001 C
b11111111011111111111111111111111000000001 ]
b11111111011111111111111111111111000000001 `
0k
0f
18
1!
#7375000
1k
1f
#7500000
0k
0f
08
0!
#7625000
1k
1f
#7750000
b1111111111011111111111111111111100000000001 X
b1111111111011111111111111111111100000000001 B
b1111111111011111111111111111111100000000001 Y
b1111111111011111111111111111111100000000001 a
b1111111111011111111111111111111100000000001 H
b1111111111011111111111111111111100000000001 V
b1111111111111111111111111111111100000000000 R
b1111111111111111111111111111111100000000000 @
b1111111111111111111111111111111100000000000 S
b111111111111111111111 L
b111111111111111111111 A
b111111111111111111111 M
b1111111111011111111111111111111100000000001 ^
b1111111111011111111111111111111100000000001 =
b1111111111011111111111111111111100000000001 _
b1111111111111111111111111111111100000000000 F
b1111111111111111111111111111111100000000000 P
b111111111011111111111111111111110000000001 I
b111111111011111111111111111111110000000001 (
b111111111111111111111 G
b111111111111111111111 J
b111111111011111111111111111111110000000001 [
b111111111011111111111111111111110000000001 C
b111111111011111111111111111111110000000001 ]
b111111111011111111111111111111110000000001 `
b111111111111111111111111111111110000000000 U
b111111111111111111111111111111110000000000 D
b111111111111111111111111111111110000000000 \
b1111111111111111111111 O
b1111111111111111111111 E
b1011 5
0k
0f
18
1!
#7875000
1k
1f
#8000000
0k
0f
08
0!
#8125000
1k
1f
#8250000
b11111111111011111111111111111111000000000001 X
b11111111111011111111111111111111000000000001 B
b11111111111011111111111111111111000000000001 Y
b11111111111011111111111111111111000000000001 a
b11111111111011111111111111111111000000000001 H
b11111111111011111111111111111111000000000001 V
b11111111111111111111111111111111000000000000 R
b11111111111111111111111111111111000000000000 @
b11111111111111111111111111111111000000000000 S
b11111111111111111111 L
b11111111111111111111 A
b11111111111111111111 M
b11111111111011111111111111111111000000000001 ^
b11111111111011111111111111111111000000000001 =
b11111111111011111111111111111111000000000001 _
b11111111111111111111111111111111000000000000 F
b11111111111111111111111111111111000000000000 P
b11111111111111111111 G
b11111111111111111111 J
b1111111111011111111111111111111100000000001 I
b1111111111011111111111111111111100000000001 (
b1100 5
b111111111111111111111 O
b111111111111111111111 E
b1111111111111111111111111111111100000000000 U
b1111111111111111111111111111111100000000000 D
b1111111111111111111111111111111100000000000 \
b1111111111011111111111111111111100000000001 [
b1111111111011111111111111111111100000000001 C
b1111111111011111111111111111111100000000001 ]
b1111111111011111111111111111111100000000001 `
0k
0f
18
1!
#8375000
1k
1f
#8500000
0k
0f
08
0!
#8625000
1k
1f
#8750000
b111111111111011111111111111111110000000000001 X
b111111111111011111111111111111110000000000001 B
b111111111111011111111111111111110000000000001 Y
b111111111111011111111111111111110000000000001 a
b111111111111011111111111111111110000000000001 H
b111111111111011111111111111111110000000000001 V
b111111111111111111111111111111110000000000000 R
b111111111111111111111111111111110000000000000 @
b111111111111111111111111111111110000000000000 S
b1111111111111111111 L
b1111111111111111111 A
b1111111111111111111 M
b111111111111011111111111111111110000000000001 ^
b111111111111011111111111111111110000000000001 =
b111111111111011111111111111111110000000000001 _
b111111111111111111111111111111110000000000000 F
b111111111111111111111111111111110000000000000 P
b11111111111011111111111111111111000000000001 I
b11111111111011111111111111111111000000000001 (
b1111111111111111111 G
b1111111111111111111 J
b11111111111011111111111111111111000000000001 [
b11111111111011111111111111111111000000000001 C
b11111111111011111111111111111111000000000001 ]
b11111111111011111111111111111111000000000001 `
b11111111111111111111111111111111000000000000 U
b11111111111111111111111111111111000000000000 D
b11111111111111111111111111111111000000000000 \
b11111111111111111111 O
b11111111111111111111 E
b1101 5
0k
0f
18
1!
#8875000
1k
1f
#9000000
0k
0f
08
0!
#9125000
1k
1f
