DataPath.v
module DataPath
(
	input wire b_sel,
	input wire a_sel,
	input wire add_sel,
	input wire prod_sel,
	input wire [31:0]Data_A,
	input wire [31:0]Data_B,
	input wire Shift_Enable,
	input wire Clock,
	input wire Reset,
	output reg [63:0]Prod,
	output wire oB_LSB

);

//-------------PARA B-----------------//
wire [31:0]Mux_B_Out;
wire [31:0]Reg_B_Out;
wire [31:0]Shifted_B;


assign	oB_LSB= Mux_B_Out[0];

MUX #(32) Mux_B
(
	.Select(b_sel),
	.Data_A(Shifted_B),
	.Data_B(Data_B),
	.Out(Mux_B_Out)
);

FFD #(32) Reg_B
(
	.Clock(Clock),
	.Reset(Reset),
	.Enable(1),
	.D(Mux_B_Out),
	.Q(Reg_B_Out)
	
);

Shift_Register_Right Shift_B
(	.Clock(Clock),
	.Data(Reg_B_Out),
	.Enable(Shift_Enable),
	.Shifted_Data(Shifted_B)
);

//--------PARA A----------//
wire [31:0]Mux_A_Out;
wire [31:0]Reg_A_Out;
wire [31:0]Shifted_A;

MUX #(32) Mux_A
(
	.Select(a_sel),
	.Data_A(Shifted_A),
	.Data_B(Data_A),
	.Out(Mux_A_Out)
);

FFD #(32) Reg_A
(
	.Clock(Clock),
	.Reset(Reset),
	.Enable(1),
	.D(Mux_A_Out),
	.Q(Reg_A_Out)
	
);

Shift_Register_Left Shift_A
(	.Clock(Clock),
	.Data(Reg_A_Out),
	.Enable(Shift_Enable),
	.Shifted_Data(Shifted_A)
);

//--------PARA EL PRODUCTO------------//
wire [63:0]Mux_Prod_Out;
wire [63:0]Add_Out;
wire [63:0]Sum_Prod;

MUX #(64) Mux_Prod1
(
	.Select(prod_sel),
	.Data_A(Sum_Prod),
	.Data_B(64'b0),
	.Out(Mux_Prod_Out)
);

wire [63:0]Product;
always @ (Product)
	Prod=Product;
	
FFD #(64) Reg_Prod
(
	.Clock(Clock),
	.Reset(Reset),
	.Enable(1),
	.D(Mux_Prod_Out),
	.Q(Product)
);

ADDER Adder_Prod
(

	.Data_A(Reg_A_Out),
	.Data_B(Product),
	.Result(Add_Out)
);

MUX #(64) Mux_Prod0
(
	.Select(add_sel),
	.Data_A(Add_Out),
	.Data_B(Product),
	.Out(Sum_Prod)
);
endmodule


///////////////////MUX//////////////////
module MUX #(parameter SIZE=32)
(
	input wire Select,
	input wire [SIZE-1:0]Data_B,
	input wire [SIZE-1:0]Data_A,
	output reg [SIZE-1:0] Out
);


always @(*)
	begin
		if(Select==1)
			Out<=Data_A;
		else if (Select==0)
			Out<=Data_B;
	end

endmodule

///////////////REGISTER///////////////
module FFD # ( parameter SIZE=32 )
(
	input wire				Clock,
	input wire				Reset,
	input wire				Enable,
	input wire [SIZE-1:0]	D,
	output reg [SIZE-1:0]	Q
);


always @ (posedge Clock) 
begin
	if ( Reset )
		Q <= 0;
	else
	begin	
		if (Enable) 
			Q <= D; 
	end	
 
end

endmodule

////////////////SHIFT REGISTER RIGHT//////////
module Shift_Register_Right
(	input wire Clock,
	input wire [31:0]Data,
	input wire Enable,
	output reg [31:0]Shifted_Data
);
	reg newClock;
initial
  begin 
 
  newClock =0;
  end
  always
	begin
   # 125 newClock  =1;
   # 125 newClock  =0;
   
	end
	always @(  posedge  newClock)
	if(Enable)
		begin
			Shifted_Data = Data>>1;
		end
	else
		begin
			Shifted_Data = Data;
		end
endmodule

////////////SHIFT REGISTER LEFT//////////////
module Shift_Register_Left
(	input wire Clock,
	input wire [31:0]Data,
	input wire Enable,
	output reg [31:0]Shifted_Data
);
reg newClock;
initial
  begin 
 
  newClock =0;
  end
  always
	begin
   # 125 newClock  =1;
   # 125 newClock  =0;
   
	end
always @(posedge newClock)
	if(Enable)
		begin
			Shifted_Data = Data<<1;
		end
	else
		begin
			Shifted_Data = Data;
		end
endmodule


////////////ADDER///////////////////////////
module ADDER
(
	input wire [31:0]Data_A,
	input wire [63:0]Data_B,
	output reg [63:0]Result
);

	always @(*)
		begin
			Result <= Data_B + Data_A;
		end
endmodule

generator.v
module probador(clk,rst,acknowledge,validdata);
output clk,rst,acknowledge,validdata;

reloj r1(clk);
reset rs(rst);
ack a1(acknowledge);
valid d1(validdata);
endmodule
//generacion del reloj
module reloj(clk);
output clk;
reg clk;  
initial
  begin 
 
  clk =0;
  end
  always
	begin
   #250 clk =1;
   #250 clk =0;
   
	end
endmodule
//generacion del reset
module reset (rst);
output rst;
reg rst;
initial
	begin
	 rst=0;
	#2 rst=~rst;
	#600 rst=~rst;
	end
endmodule

module ack (acknowledge);
output acknowledge;
reg acknowledge;
initial
	begin
	
	 acknowledge=0;
	#20000 acknowledge=~acknowledge;
	#400 acknowledge=~acknowledge;
	end
endmodule

module valid (validdata);
output validdata;
reg validdata;
initial
	begin
	
	validdata=0;
	#1000 validdata=~validdata;
	#500 validdata=~validdata;
	end
endmodule

controlMachine.v

`define STATE_IDLE 0
`define STATE_CALC 1
`define STATE_DONE 2





//------------------------------------------------



module control_Machine
  (
    input wire Clock,
    input wire Reset,
    input wire iLSB,   
    input wire iValid_Data,
    input wire iAck,
    output reg oShift,
    output reg  oA_Sel,
    output reg oB_Sel,
    output reg oProduct_Sel,
    output reg oAdd_Sel
  );
  //Registros  internos del controlador
  
  reg [5:0] rCounter;
  reg [1:0]rCurrentState;
  reg  [1:0]rNextState;
  reg rCountReset;
  reg firstBit;

  //Next State and delay logic
  always @ ( posedge Clock )
    if (Reset)
      begin
        rCurrentState = `STATE_IDLE;
        rCountReset <=1'b1;
        firstBit <=1'b0;
        
       
      end
  else
		begin
      rCurrentState <= rNextState;
      if(rCountReset)
      begin
      rCounter<= 6'd0;
      end
      
      else
      
     begin
     rCounter<=  rCounter + 6'd1;
     end
		end
    

  //----------------------------------------------
  //Current state and output logic
  always @ ( * )
    begin
      case (rCurrentState)
        //------------------------------------------
        `STATE_IDLE:
          begin
          rCountReset=1'b1;
          oShift=1'b0;
         oA_Sel=1'b0;
         oB_Sel=1'b0;
         oProduct_Sel=1'b0;
         oAdd_Sel=1'b0;
         if(iValid_Data)
			begin
            rNextState = `STATE_CALC;
            rCountReset=1'b0;
           firstBit=1'b1;
            end
          else
			begin
			rNextState= `STATE_IDLE;
			end
          end
//------------------------------------------
/*

*/
      `STATE_CALC:
        begin
       /* if(firstBit)
        begin
        oA_Sel=1'b0;
         oB_Sel=1'b0;
            oProduct_Sel=1'b0;
            firstBit=1'b0;
        end
        else
        begin*/
         oA_Sel=1'b1;
         oB_Sel=1'b1;
            oProduct_Sel=1'b1;
           // end
         if(iLSB)
         begin
           oShift=1'b1;
           oAdd_Sel=1'b0;
           end
           else
           begin
           oShift=1'b1;
           oAdd_Sel=1'b1;
           end
           
       if(rCounter<6'd32)
       begin
       rNextState=`STATE_CALC;
       end    
       else
       begin 
        rNextState=`STATE_DONE;
         rCountReset=1'b1;
       end
          
          
          
          
        end
//------------------------------------------
/*

  */
      `STATE_DONE:
        begin
          rCounter= 6'd0;
          oShift=1'b0;
         oAdd_Sel=1'b0;
          if ( iAck)
            rNextState = `STATE_IDLE;
          else
            rNextState = `STATE_DONE;
        end

//------------------------------------------
        
 
        default:
          begin
            rNextState = `STATE_IDLE;
          end
        //------------------------------------------
      endcase
    end
endmodule

testbench.v
`timescale 1ns/1ps
`include "controlMachine.v"
`include "generator.v"
`include "DataPath.v"
module BancoPruebas;
wire Clock,Reset,wAck,wValidData;
wire oShift,oA_Sel,oB_Sel, oProduct_Sel,oAdd_Sel, wiLSB;
reg [31:0] dataA=32'd10;
reg [31:0] dataB=32'd349525;
wire [63:0] product;

control_Machine control1(.Clock(Clock),.Reset(Reset),.iLSB(wiLSB),.iValid_Data(wValidData),.iAck(wAck),.oShift(oShift),.oA_Sel(oA_Sel),.oB_Sel(oB_Sel),.oProduct_Sel(oProduct_Sel),.oAdd_Sel(oAdd_Sel));
probador p1(.clk(Clock),.rst(Reset),.acknowledge(wAck),.validdata(wValidData));

DataPath data1(
	.b_sel(oB_Sel), .a_sel(oA_Sel), .prod_sel(oProduct_Sel), .Data_A(dataA), .Data_B(dataB), .Shift_Enable(oShift), .Clock(Clock), .Reset(Reset), .Prod(product), .oB_LSB(wiLSB));



 initial 
  begin
    $dumpfile("signals.vcd");
    $dumpvars;
    #70000 ;
    $display ("Test finished");
    $finish;
   
  end
endmodule

signals.vcd
$date
	Mon May 11 22:08:08 2015
$end
$version
	Icarus Verilog
$end
$timescale
	1ps
$end
$scope module BancoPruebas $end
$var wire 1 ! Clock $end
$var wire 1 " Reset $end
$var wire 1 # oA_Sel $end
$var wire 1 $ oAdd_Sel $end
$var wire 1 % oB_Sel $end
$var wire 1 & oProduct_Sel $end
$var wire 1 ' oShift $end
$var wire 64 ( product [63:0] $end
$var wire 1 ) wAck $end
$var wire 1 * wValidData $end
$var wire 1 + wiLSB $end
$var reg 32 , dataA [31:0] $end
$var reg 32 - dataB [31:0] $end
$scope module control1 $end
$var wire 1 ! Clock $end
$var wire 1 " Reset $end
$var wire 1 ) iAck $end
$var wire 1 + iLSB $end
$var wire 1 * iValid_Data $end
$var reg 1 . firstBit $end
$var reg 1 / oA_Sel $end
$var reg 1 0 oAdd_Sel $end
$var reg 1 1 oB_Sel $end
$var reg 1 2 oProduct_Sel $end
$var reg 1 3 oShift $end
$var reg 1 4 rCountReset $end
$var reg 6 5 rCounter [5:0] $end
$var reg 2 6 rCurrentState [1:0] $end
$var reg 2 7 rNextState [1:0] $end
$upscope $end
$scope module p1 $end
$var wire 1 ) acknowledge $end
$var wire 1 ! clk $end
$var wire 1 " rst $end
$var wire 1 * validdata $end
$scope module r1 $end
$var reg 1 8 clk $end
$upscope $end
$scope module rs $end
$var reg 1 9 rst $end
$upscope $end
$scope module a1 $end
$var reg 1 : acknowledge $end
$upscope $end
$scope module d1 $end
$var reg 1 ; validdata $end
$upscope $end
$upscope $end
$scope module data1 $end
$var wire 64 < Add_Out [63:0] $end
$var wire 1 ! Clock $end
$var wire 32 = Data_A [31:0] $end
$var wire 32 > Data_B [31:0] $end
$var wire 32 ? Mux_A_Out [31:0] $end
$var wire 32 @ Mux_B_Out [31:0] $end
$var wire 64 A Mux_Prod_Out [63:0] $end
$var wire 64 B Product [63:0] $end
$var wire 32 C Reg_A_Out [31:0] $end
$var wire 32 D Reg_B_Out [31:0] $end
$var wire 1 " Reset $end
$var wire 1 ' Shift_Enable $end
$var wire 32 E Shifted_A [31:0] $end
$var wire 32 F Shifted_B [31:0] $end
$var wire 64 G Sum_Prod [63:0] $end
$var wire 1 # a_sel $end
$var wire 1 H add_sel $end
$var wire 1 % b_sel $end
$var wire 1 + oB_LSB $end
$var wire 1 & prod_sel $end
$var reg 64 I Prod [63:0] $end
$scope module Mux_B $end
$var wire 32 J Data_A [31:0] $end
$var wire 32 K Data_B [31:0] $end
$var wire 1 % Select $end
$var reg 32 L Out [31:0] $end
$upscope $end
$scope module Reg_B $end
$var wire 1 ! Clock $end
$var wire 32 M D [31:0] $end
$var wire 1 N Enable $end
$var wire 1 " Reset $end
$var reg 32 O Q [31:0] $end
$upscope $end
$scope module Shift_B $end
$var wire 1 ! Clock $end
$var wire 32 P Data [31:0] $end
$var wire 1 ' Enable $end
$var reg 32 Q Shifted_Data [31:0] $end
$var reg 1 R newClock $end
$upscope $end
$scope module Mux_A $end
$var wire 32 S Data_A [31:0] $end
$var wire 32 T Data_B [31:0] $end
$var wire 1 # Select $end
$var reg 32 U Out [31:0] $end
$upscope $end
$scope module Reg_A $end
$var wire 1 ! Clock $end
$var wire 32 V D [31:0] $end
$var wire 1 W Enable $end
$var wire 1 " Reset $end
$var reg 32 X Q [31:0] $end
$upscope $end
$scope module Shift_A $end
$var wire 1 ! Clock $end
$var wire 32 Y Data [31:0] $end
$var wire 1 ' Enable $end
$var reg 32 Z Shifted_Data [31:0] $end
$var reg 1 [ newClock $end
$upscope $end
$scope module Mux_Prod1 $end
$var wire 64 \ Data_A [63:0] $end
$var wire 64 ] Data_B [63:0] $end
$var wire 1 & Select $end
$var reg 64 ^ Out [63:0] $end
$upscope $end
$scope module Reg_Prod $end
$var wire 1 ! Clock $end
$var wire 64 _ D [63:0] $end
$var wire 1 ` Enable $end
$var wire 1 " Reset $end
$var reg 64 a Q [63:0] $end
$upscope $end
$scope module Adder_Prod $end
$var wire 32 b Data_A [31:0] $end
$var wire 64 c Data_B [63:0] $end
$var reg 64 d Result [63:0] $end
$upscope $end
$scope module Mux_Prod0 $end
$var wire 64 e Data_A [63:0] $end
$var wire 64 f Data_B [63:0] $end
$var wire 1 H Select $end
$var reg 64 g Out [63:0] $end
$upscope $end
$upscope $end
$upscope $end
$enddefinitions $end
#0
$dumpvars
bx g
bx f
bx e
bx d
bx c
bx b
bx a
1`
bx _
bx ^
b0 ]
bx \
0[
bx Z
bx Y
bx X
1W
bx V
bx U
b1010 T
bx S
0R
bx Q
bx P
bx O
1N
bx M
bx L
b1010101010101010101 K
bx J
bx I
zH
bx G
bx F
bx E
bx D
bx C
bx B
bx A
bx @
bx ?
b1010101010101010101 >
b1010 =
bx <
0;
0:
09
08
b0 7
bx 6
bx 5
x4
x3
x2
x1
x0
x/
x.
b1010101010101010101 -
b1010 ,
x+
0*
0)
bx (
x'
x&
x%
x$
x#
0"
0!
$end
#2000
19
1"
#125000
1[
1R
#250000
b0 d
b0 <
b0 e
1+
b0 I
b0 (
b0 ^
b0 A
b0 _
b1010101010101010101 L
b1010101010101010101 @
b1010101010101010101 M
b1010 U
b1010 ?
b1010 V
0.
b0 O
b0 D
b0 P
b0 X
b0 C
b0 Y
b0 b
b0 a
b0 B
b0 c
b0 f
00
0$
02
0&
01
0%
0/
0#
03
0'
14
b0 6
0[
0R
18
1!
#375000
b0 Z
b0 E
b0 S
b0 Q
b0 F
b0 J
1[
1R
#500000
0[
0R
08
0!
#502000
09
0"
#625000
1[
1R
#750000
b1010 d
b1010 <
b1010 e
b1010 X
b1010 C
b1010 Y
b1010 b
b1010101010101010101 O
b1010101010101010101 D
b1010101010101010101 P
b0 5
0[
0R
18
1!
#875000
b1010 Z
b1010 E
b1010 S
b1010101010101010101 Q
b1010101010101010101 F
b1010101010101010101 J
1[
1R
#1000000
0[
0R
08
0!
#1125000
1[
1R
#1250000
0[
0R
18
1!
#1375000
1[
1R
#1500000
0[
0R
08
0!
#1625000
1[
1R
#1750000
0[
0R
18
1!
#1875000
1[
1R
#2000000
0[
0R
08
0!
#2125000
1[
1R
#2250000
0[
0R
18
1!
#2375000
1[
1R
#2500000
1.
04
b1 7
0[
0R
08
0!
1;
1*
#2625000
1[
1R
#2750000
bx ^
bx A
bx _
13
1'
12
1&
11
1%
1/
1#
b1 5
b1 6
0[
0R
18
1!
#2875000
10
1$
0+
b10100 U
b10100 ?
b10100 V
b101010101010101010 L
b101010101010101010 @
b101010101010101010 M
b10100 Z
b10100 E
b10100 S
b101010101010101010 Q
b101010101010101010 F
b101010101010101010 J
1[
1R
#3000000
0[
0R
08
0!
0;
0*
#3125000
1[
1R
#3250000
bx d
bx <
bx e
bx I
bx (
b10 5
b101010101010101010 O
b101010101010101010 D
b101010101010101010 P
b10100 X
b10100 C
b10100 Y
b10100 b
bx a
bx B
bx c
bx f
0[
0R
18
1!
#3375000
00
0$
1+
b101000 U
b101000 ?
b101000 V
b10101010101010101 L
b10101010101010101 @
b10101010101010101 M
b101000 Z
b101000 E
b101000 S
b10101010101010101 Q
b10101010101010101 F
b10101010101010101 J
1[
1R
#3500000
0[
0R
08
0!
#3625000
1[
1R
#3750000
b101000 X
b101000 C
b101000 Y
b101000 b
b10101010101010101 O
b10101010101010101 D
b10101010101010101 P
b11 5
0[
0R
18
1!
#3875000
10
1$
0+
b1010000 U
b1010000 ?
b1010000 V
b1010101010101010 L
b1010101010101010 @
b1010101010101010 M
b1010000 Z
b1010000 E
b1010000 S
b1010101010101010 Q
b1010101010101010 F
b1010101010101010 J
1[
1R
#4000000
0[
0R
08
0!
#4125000
1[
1R
#4250000
b100 5
b1010101010101010 O
b1010101010101010 D
b1010101010101010 P
b1010000 X
b1010000 C
b1010000 Y
b1010000 b
0[
0R
18
1!
#4375000
00
0$
1+
b10100000 U
b10100000 ?
b10100000 V
b101010101010101 L
b101010101010101 @
b101010101010101 M
b10100000 Z
b10100000 E
b10100000 S
b101010101010101 Q
b101010101010101 F
b101010101010101 J
1[
1R
#4500000
0[
0R
08
0!
#4625000
1[
1R
#4750000
b10100000 X
b10100000 C
b10100000 Y
b10100000 b
b101010101010101 O
b101010101010101 D
b101010101010101 P
b101 5
0[
0R
18
1!
#4875000
10
1$
0+
b101000000 U
b101000000 ?
b101000000 V
b10101010101010 L
b10101010101010 @
b10101010101010 M
b101000000 Z
b101000000 E
b101000000 S
b10101010101010 Q
b10101010101010 F
b10101010101010 J
1[
1R
#5000000
0[
0R
08
0!
#5125000
1[
1R
#5250000
b110 5
b10101010101010 O
b10101010101010 D
b10101010101010 P
b101000000 X
b101000000 C
b101000000 Y
b101000000 b
0[
0R
18
1!
#5375000
00
0$
1+
b1010000000 U
b1010000000 ?
b1010000000 V
b1010101010101 L
b1010101010101 @
b1010101010101 M
b1010000000 Z
b1010000000 E
b1010000000 S
b1010101010101 Q
b1010101010101 F
b1010101010101 J
1[
1R
#5500000
0[
0R
08
0!
#5625000
1[
1R
#5750000
b1010000000 X
b1010000000 C
b1010000000 Y
b1010000000 b
b1010101010101 O
b1010101010101 D
b1010101010101 P
b111 5
0[
0R
18
1!
#5875000
10
1$
0+
b10100000000 U
b10100000000 ?
b10100000000 V
b101010101010 L
b101010101010 @
b101010101010 M
b10100000000 Z
b10100000000 E
b10100000000 S
b101010101010 Q
b101010101010 F
b101010101010 J
1[
1R
#6000000
0[
0R
08
0!
#6125000
1[
1R
#6250000
b1000 5
b101010101010 O
b101010101010 D
b101010101010 P
b10100000000 X
b10100000000 C
b10100000000 Y
b10100000000 b
0[
0R
18
1!
#6375000
00
0$
1+
b101000000000 U
b101000000000 ?
b101000000000 V
b10101010101 L
b10101010101 @
b10101010101 M
b101000000000 Z
b101000000000 E
b101000000000 S
b10101010101 Q
b10101010101 F
b10101010101 J
1[
1R
#6500000
0[
0R
08
0!
#6625000
1[
1R
#6750000
b101000000000 X
b101000000000 C
b101000000000 Y
b101000000000 b
b10101010101 O
b10101010101 D
b10101010101 P
b1001 5
0[
0R
18
1!
#6875000
10
1$
0+
b1010000000000 U
b1010000000000 ?
b1010000000000 V
b1010101010 L
b1010101010 @
b1010101010 M
b1010000000000 Z
b1010000000000 E
b1010000000000 S
b1010101010 Q
b1010101010 F
b1010101010 J
1[
1R
#7000000
0[
0R
08
0!
#7125000
1[
1R
#7250000
b1010 5
b1010101010 O
b1010101010 D
b1010101010 P
b1010000000000 X
b1010000000000 C
b1010000000000 Y
b1010000000000 b
0[
0R
18
1!
#7375000
00
0$
1+
b10100000000000 U
b10100000000000 ?
b10100000000000 V
b101010101 L
b101010101 @
b101010101 M
b10100000000000 Z
b10100000000000 E
b10100000000000 S
b101010101 Q
b101010101 F
b101010101 J
1[
1R
#7500000
0[
0R
08
0!
#7625000
1[
1R
#7750000
b10100000000000 X
b10100000000000 C
b10100000000000 Y
b10100000000000 b
b101010101 O
b101010101 D
b101010101 P
b1011 5
0[
0R
18
1!
#7875000
10
1$
0+
b101000000000000 U
b101000000000000 ?
b101000000000000 V
b10101010 L
b10101010 @
b10101010 M
b101000000000000 Z
b101000000000000 E
b101000000000000 S
b10101010 Q
b10101010 F
b10101010 J
1[
1R
#8000000
0[
0R
08
0!
#8125000
1[
1R
#8250000
b1100 5
b10101010 O
b10101010 D
b10101010 P
b101000000000000 X
b101000000000000 C
b101000000000000 Y
b101000000000000 b
0[
0R
18
1!
#8375000
00
0$
1+
b1010000000000000 U
b1010000000000000 ?
b1010000000000000 V
b1010101 L
b1010101 @
b1010101 M
b1010000000000000 Z
b1010000000000000 E
b1010000000000000 S
b1010101 Q
b1010101 F
b1010101 J
1[
1R
#8500000
0[
0R
08
0!
#8625000
1[
1R
#8750000
b1010000000000000 X
b1010000000000000 C
b1010000000000000 Y
b1010000000000000 b
b1010101 O
b1010101 D
b1010101 P
b1101 5
0[
0R
18
1!
#8875000
10
1$
0+
b10100000000000000 U
b10100000000000000 ?
b10100000000000000 V
b101010 L
b101010 @
b101010 M
b10100000000000000 Z
b10100000000000000 E
b10100000000000000 S
b101010 Q
b101010 F
b101010 J
1[
1R
#9000000
0[
0R
08
0!
#9125000
1[
1R
#9250000
b1110 5
b101010 O
b101010 D
b101010 P
b10100000000000000 X
b10100000000000000 C
b10100000000000000 Y
b10100000000000000 b
0[
0R
18
1!
#9375000
00
0$
1+
b101000000000000000 U
b101000000000000000 ?
b101000000000000000 V
b10101 L
b10101 @
b10101 M
b101000000000000000 Z
b101000000000000000 E
b101000000000000000 S
b10101 Q
b10101 F
b10101 J
1[
1R
#9500000
0[
0R
08
0!
#9625000
1[
1R
#9750000
b101000000000000000 X
b101000000000000000 C
b101000000000000000 Y
b101000000000000000 b
b10101 O
b10101 D
b10101 P
b1111 5
0[
0R
18
1!
#9875000
10
1$
0+
b1010000000000000000 U
b1010000000000000000 ?
b1010000000000000000 V
b1010 L
b1010 @
b1010 M
b1010000000000000000 Z
b1010000000000000000 E
b1010000000000000000 S
b1010 Q
b1010 F
b1010 J
1[
1R
#10000000
0[
0R
08
0!
#10125000
1[
1R
#10250000
b10000 5
b1010 O
b1010 D
b1010 P
b1010000000000000000 X
b1010000000000000000 C
b1010000000000000000 Y
b1010000000000000000 b
0[
0R
18
1!
#10375000
00
0$
1+
b10100000000000000000 U
b10100000000000000000 ?
b10100000000000000000 V
b101 L
b101 @
b101 M
b10100000000000000000 Z
b10100000000000000000 E
b10100000000000000000 S
b101 Q
b101 F
b101 J
1[
1R
#10500000
0[
0R
08
0!
#10625000
1[
1R
#10750000
b10100000000000000000 X
b10100000000000000000 C
b10100000000000000000 Y
b10100000000000000000 b
b101 O
b101 D
b101 P
b10001 5
0[
0R
18
1!
#10875000
10
1$
0+
b101000000000000000000 U
b101000000000000000000 ?
b101000000000000000000 V
b10 L
b10 @
b10 M
b101000000000000000000 Z
b101000000000000000000 E
b101000000000000000000 S
b10 Q
b10 F
b10 J
1[
1R
#11000000
0[
0R
08
0!
#11125000
1[
1R
#11250000
b10010 5
b10 O
b10 D
b10 P
b101000000000000000000 X
b101000000000000000000 C
b101000000000000000000 Y
b101000000000000000000 b
0[
0R
18
1!
#11375000
00
0$
1+
b1010000000000000000000 U
b1010000000000000000000 ?
b1010000000000000000000 V
b1 L
b1 @
b1 M
b1010000000000000000000 Z
b1010000000000000000000 E
b1010000000000000000000 S
b1 Q
b1 F
b1 J
1[
1R
#11500000
0[
0R
08
0!
#11625000
1[
1R
#11750000
b1010000000000000000000 X
b1010000000000000000000 C
b1010000000000000000000 Y
b1010000000000000000000 b
b1 O
b1 D
b1 P
b10011 5
0[
0R
18
1!
#11875000
10
1$
0+
b10100000000000000000000 U
b10100000000000000000000 ?
b10100000000000000000000 V
b0 L
b0 @
b0 M
b10100000000000000000000 Z
b10100000000000000000000 E
b10100000000000000000000 S
b0 Q
b0 F
b0 J
1[
1R
#12000000
0[
0R
08
0!
#12125000
1[
1R
#12250000
b10100 5
b0 O
b0 D
b0 P
b10100000000000000000000 X
b10100000000000000000000 C
b10100000000000000000000 Y
b10100000000000000000000 b
0[
0R
18
1!
#12375000
b101000000000000000000000 U
b101000000000000000000000 ?
b101000000000000000000000 V
b101000000000000000000000 Z
b101000000000000000000000 E
b101000000000000000000000 S
1[
1R
#12500000
0[
0R
08
0!
#12625000
1[
1R
#12750000
b101000000000000000000000 X
b101000000000000000000000 C
b101000000000000000000000 Y
b101000000000000000000000 b
b10101 5
0[
0R
18
1!
#12875000
b1010000000000000000000000 U
b1010000000000000000000000 ?
b1010000000000000000000000 V
b1010000000000000000000000 Z
b1010000000000000000000000 E
b1010000000000000000000000 S
1[
1R
#13000000
0[
0R
08
0!
#13125000
1[
1R
#13250000
b10110 5
b1010000000000000000000000 X
b1010000000000000000000000 C
b1010000000000000000000000 Y
b1010000000000000000000000 b
0[
0R
18
1!
#13375000
b10100000000000000000000000 U
b10100000000000000000000000 ?
b10100000000000000000000000 V
b10100000000000000000000000 Z
b10100000000000000000000000 E
b10100000000000000000000000 S
1[
1R
#13500000
0[
0R
08
0!
#13625000
1[
1R
#13750000
b10100000000000000000000000 X
b10100000000000000000000000 C
b10100000000000000000000000 Y
b10100000000000000000000000 b
b10111 5
0[
0R
18
1!
#13875000
b101000000000000000000000000 U
b101000000000000000000000000 ?
b101000000000000000000000000 V
b101000000000000000000000000 Z
b101000000000000000000000000 E
b101000000000000000000000000 S
1[
1R
#14000000
0[
0R
08
0!
#14125000
1[
1R
#14250000
b11000 5
b101000000000000000000000000 X
b101000000000000000000000000 C
b101000000000000000000000000 Y
b101000000000000000000000000 b
0[
0R
18
1!
#14375000
b1010000000000000000000000000 U
b1010000000000000000000000000 ?
b1010000000000000000000000000 V
b1010000000000000000000000000 Z
b1010000000000000000000000000 E
b1010000000000000000000000000 S
1[
1R
#14500000
0[
0R
08
0!
#14625000
1[
1R
#14750000
b1010000000000000000000000000 X
b1010000000000000000000000000 C
b1010000000000000000000000000 Y
b1010000000000000000000000000 b
b11001 5
0[
0R
18
1!
#14875000
b10100000000000000000000000000 U
b10100000000000000000000000000 ?
b10100000000000000000000000000 V
b10100000000000000000000000000 Z
b10100000000000000000000000000 E
b10100000000000000000000000000 S
1[
1R
#15000000
0[
0R
08
0!
#15125000
1[
1R
#15250000
b11010 5
b10100000000000000000000000000 X
b10100000000000000000000000000 C
b10100000000000000000000000000 Y
b10100000000000000000000000000 b
0[
0R
18
1!
#15375000
b101000000000000000000000000000 U
b101000000000000000000000000000 ?
b101000000000000000000000000000 V
b101000000000000000000000000000 Z
b101000000000000000000000000000 E
b101000000000000000000000000000 S
1[
1R
#15500000
0[
0R
08
0!
#15625000
1[
1R
#15750000
b101000000000000000000000000000 X
b101000000000000000000000000000 C
b101000000000000000000000000000 Y
b101000000000000000000000000000 b
b11011 5
0[
0R
18
1!
#15875000
b1010000000000000000000000000000 U
b1010000000000000000000000000000 ?
b1010000000000000000000000000000 V
b1010000000000000000000000000000 Z
b1010000000000000000000000000000 E
b1010000000000000000000000000000 S
1[
1R
#16000000
0[
0R
08
0!
#16125000
1[
1R
#16250000
b11100 5
b1010000000000000000000000000000 X
b1010000000000000000000000000000 C
b1010000000000000000000000000000 Y
b1010000000000000000000000000000 b
0[
0R
18
1!
#16375000
b10100000000000000000000000000000 U
b10100000000000000000000000000000 ?
b10100000000000000000000000000000 V
b10100000000000000000000000000000 Z
b10100000000000000000000000000000 E
b10100000000000000000000000000000 S
1[
1R
#16500000
0[
0R
08
0!
#16625000
1[
1R
#16750000
b10100000000000000000000000000000 X
b10100000000000000000000000000000 C
b10100000000000000000000000000000 Y
b10100000000000000000000000000000 b
b11101 5
0[
0R
18
1!
#16875000
b1000000000000000000000000000000 U
b1000000000000000000000000000000 ?
b1000000000000000000000000000000 V
b1000000000000000000000000000000 Z
b1000000000000000000000000000000 E
b1000000000000000000000000000000 S
1[
1R
#17000000
0[
0R
08
0!
#17125000
1[
1R
#17250000
b11110 5
b1000000000000000000000000000000 X
b1000000000000000000000000000000 C
b1000000000000000000000000000000 Y
b1000000000000000000000000000000 b
0[
0R
18
1!
#17375000
b10000000000000000000000000000000 U
b10000000000000000000000000000000 ?
b10000000000000000000000000000000 V
b10000000000000000000000000000000 Z
b10000000000000000000000000000000 E
b10000000000000000000000000000000 S
1[
1R
#17500000
0[
0R
08
0!
#17625000
1[
1R
#17750000
b10000000000000000000000000000000 X
b10000000000000000000000000000000 C
b10000000000000000000000000000000 Y
b10000000000000000000000000000000 b
b11111 5
0[
0R
18
1!
#17875000
b0 U
b0 ?
b0 V
b0 Z
b0 E
b0 S
1[
1R
#18000000
0[
0R
08
0!
#18125000
1[
1R
#18250000
14
b10 7
b100000 5
b0 X
b0 C
b0 Y
b0 b
0[
0R
18
1!
#18375000
1[
1R
#18500000
0[
0R
08
0!
#18625000
1[
1R
#18750000
00
0$
03
0'
b0 5
b10 6
0[
0R
18
1!
